[
  {
    "text": "Sorry for inconvenience price of s1 sport till 17 aug is 1,59,999 then it will hike",
    "author": "@BadassRitzX29",
    "likes": 9,
    "time": 1755266304,
    "date": "2025-08-15 13:58:24",
    "video_id": "2b6Jr6YKKLo",
    "is_reply": false,
    "extraction_method": "youtube_api",
    "sentiment": "negative",
    "sentiment_score": 0.7539771199226379,
    "oem": "Ola Electric",
    "month": "2025-01"
  },
  {
    "text": "Don't buy ola it's very pathetic service ever seen",
    "author": "@midhunm6176",
    "likes": 0,
    "time": 1755418341,
    "date": "2025-08-17 08:12:21",
    "video_id": "2b6Jr6YKKLo",
    "is_reply": false,
    "extraction_method": "youtube_api",
    "sentiment": "negative",
    "sentiment_score": 0.9634494781494141,
    "oem": "Ola Electric",
    "month": "2025-01"
  },
  {
    "text": "Book karne ke baad bhi price badha hi dega. Bhavish ka dhokha hawa ka jhoka🎉🎉🎉🎉 kitna jhuth bolta hai ye aadmi",
    "author": "@BHUPENDRA24J94",
    "likes": 0,
    "time": 1755400688,
    "date": "2025-08-17 03:18:08",
    "video_id": "2b6Jr6YKKLo",
    "is_reply": false,
    "extraction_method": "youtube_api",
    "sentiment": "positive",
    "sentiment_score": 0.3939487040042877,
    "oem": "Ola Electric",
    "month": "2025-01"
  },
  {
    "text": "Bhai ola scooter mat lena main fas chuka hun agar aapko kharidna hai to ek bar service centre per jakar dekho ola company ka jhooth samne a jaega scooter best kahate Hain sem de mein hamari service Aisa kuchh nahin hai 21 din se mera service centre per hai",
    "author": "@PradeepKumar-ss9kj",
    "likes": 0,
    "time": 1755367058,
    "date": "2025-08-16 17:57:38",
    "video_id": "2b6Jr6YKKLo",
    "is_reply": false,
    "extraction_method": "youtube_api",
    "sentiment": "negative",
    "sentiment_score": 0.3538515269756317,
    "oem": "Ola Electric",
    "month": "2025-01"
  },
  {
    "text": "Booked",
    "author": "@haridarshan2472",
    "likes": 0,
    "time": 1755339851,
    "date": "2025-08-16 10:24:11",
    "video_id": "2b6Jr6YKKLo",
    "is_reply": false,
    "extraction_method": "youtube_api",
    "sentiment": "neutral",
    "sentiment_score": 0.5446208119392395,
    "oem": "Ola Electric",
    "month": "2025-01"
  },
  {
    "text": "Top speed 152kmph on this tiny wheels?expected  Battery life on this new bharat cell?",
    "author": "@murugan36",
    "likes": 0,
    "time": 1755334995,
    "date": "2025-08-16 09:03:15",
    "video_id": "2b6Jr6YKKLo",
    "is_reply": false,
    "extraction_method": "youtube_api",
    "sentiment": "neutral",
    "sentiment_score": 0.659536600112915,
    "oem": "Ola Electric",
    "month": "2025-01"
  },
  {
    "text": "What about after sale service 😂",
    "author": "@haroonpaul1997",
    "likes": 0,
    "time": 1755332732,
    "date": "2025-08-16 08:25:32",
    "video_id": "2b6Jr6YKKLo",
    "is_reply": false,
    "extraction_method": "youtube_api",
    "sentiment": "neutral",
    "sentiment_score": 0.7096220850944519,
    "oem": "Ola Electric",
    "month": "2025-01"
  },
  {
    "text": "I have left my ola. Too costly service. Too costly spare parts.",
    "author": "@kislaychandan3652",
    "likes": 0,
    "time": 1755330078,
    "date": "2025-08-16 07:41:18",
    "video_id": "2b6Jr6YKKLo",
    "is_reply": false,
    "extraction_method": "youtube_api",
    "sentiment": "negative",
    "sentiment_score": 0.9221466183662415,
    "oem": "Ola Electric",
    "month": "2025-01"
  },
  {
    "text": "Don't buy Ola scooter, I have purchased ola scooter in dec-2024 , now it is in service centre from last month , The service centre is not responding, there service centre are full of ola scooter that has to be repaired,\nWhen I call service centre they are always saying It will take 1 month more and one month already passed  , My work has been disturbed and I am travelling through the bus , My money is wasted in ola scooter.\nIt's a fraud company ola electric.\nOnce your vehicle got problem it will be in the service centre forever.\n\nSo think before purchasing ola scooter and it's bike .",
    "author": "@skeditzs06",
    "likes": 1,
    "time": 1755326232,
    "date": "2025-08-16 06:37:12",
    "video_id": "2b6Jr6YKKLo",
    "is_reply": false,
    "extraction_method": "youtube_api",
    "sentiment": "negative",
    "sentiment_score": 0.8445326089859009,
    "oem": "Ola Electric",
    "month": "2025-01"
  },
  {
    "text": "Roadster pro ka pata nhi chala 1 saal pahle launch hui thi",
    "author": "@alonedhiraj2.0",
    "likes": 1,
    "time": 1755323999,
    "date": "2025-08-16 05:59:59",
    "video_id": "2b6Jr6YKKLo",
    "is_reply": false,
    "extraction_method": "youtube_api",
    "sentiment": "neutral",
    "sentiment_score": 0.5239212512969971,
    "oem": "Ola Electric",
    "month": "2025-01"
  },
  {
    "text": "Just Like Modi... Feku company.",
    "author": "@sumit55z",
    "likes": 0,
    "time": 1755320546,
    "date": "2025-08-16 05:02:26",
    "video_id": "2b6Jr6YKKLo",
    "is_reply": false,
    "extraction_method": "youtube_api",
    "sentiment": "negative",
    "sentiment_score": 0.7943585515022278,
    "oem": "Ola Electric",
    "month": "2025-01"
  },
  {
    "text": "Fukkat bhi nahi chahiye. Ola is a scam! Poor quality, poor parts, fake range, Fake claims, Worst Service throughout the country. Main 1.5 Laak ka Vada Pao kalu per ye nahi parvadega!",
    "author": "@sameermirajkar184",
    "likes": 0,
    "time": 1755319423,
    "date": "2025-08-16 04:43:43",
    "video_id": "2b6Jr6YKKLo",
    "is_reply": false,
    "extraction_method": "youtube_api",
    "sentiment": "negative",
    "sentiment_score": 0.739831268787384,
    "oem": "Ola Electric",
    "month": "2025-01"
  },
  {
    "text": "Rone ka man kare to ola lelo..",
    "author": "@pnaskar551",
    "likes": 0,
    "time": 1755316287,
    "date": "2025-08-16 03:51:27",
    "video_id": "2b6Jr6YKKLo",
    "is_reply": false,
    "extraction_method": "youtube_api",
    "sentiment": "positive",
    "sentiment_score": 0.3576121926307678,
    "oem": "Ola Electric",
    "month": "2025-01"
  },
  {
    "text": "It's better stand half a day at service center before u go to buy any ola either bike or scooty",
    "author": "@sureshKumar-it5dl",
    "likes": 0,
    "time": 1755314947,
    "date": "2025-08-16 03:29:07",
    "video_id": "2b6Jr6YKKLo",
    "is_reply": false,
    "extraction_method": "youtube_api",
    "sentiment": "neutral",
    "sentiment_score": 0.6460893154144287,
    "oem": "Ola Electric",
    "month": "2025-01"
  },
  {
    "text": "Itne power ki motor ki zaroorat nahi hai , reliblity chaheye",
    "author": "@dhananjaysharma4203",
    "likes": 0,
    "time": 1755294740,
    "date": "2025-08-15 21:52:20",
    "video_id": "2b6Jr6YKKLo",
    "is_reply": false,
    "extraction_method": "youtube_api",
    "sentiment": "negative",
    "sentiment_score": 0.4069305658340454,
    "oem": "Ola Electric",
    "month": "2025-01"
  },
  {
    "text": "Ola s1 pro jen 2 ka showroom belt price kitna hoga...........?",
    "author": "@masoodms8720",
    "likes": 0,
    "time": 1755282065,
    "date": "2025-08-15 18:21:05",
    "video_id": "2b6Jr6YKKLo",
    "is_reply": false,
    "extraction_method": "youtube_api",
    "sentiment": "neutral",
    "sentiment_score": 0.7306718230247498,
    "oem": "Ola Electric",
    "month": "2025-01"
  },
  {
    "text": "Hello sir ola s1 pro jen 2 ka battery exchange karke new cell 4780 cell ka battery 🔋 diyega kya........?",
    "author": "@masoodms8720",
    "likes": 1,
    "time": 1755281981,
    "date": "2025-08-15 18:19:41",
    "video_id": "2b6Jr6YKKLo",
    "is_reply": false,
    "extraction_method": "youtube_api",
    "sentiment": "neutral",
    "sentiment_score": 0.5093951225280762,
    "oem": "Ola Electric",
    "month": "2025-01"
  },
  {
    "text": "bhai mai to comment box me aa gaya, video baad me dekhunga",
    "author": "@Windytigor678",
    "likes": 1,
    "time": 1755278723,
    "date": "2025-08-15 17:25:23",
    "video_id": "2b6Jr6YKKLo",
    "is_reply": false,
    "extraction_method": "youtube_api",
    "sentiment": "neutral",
    "sentiment_score": 0.3556913137435913,
    "oem": "Ola Electric",
    "month": "2025-01"
  },
  {
    "text": "Bc ola s1 z ki june mein delivery start honi thi abhi tak uska koi ata pta nhi. Ola = scam",
    "author": "@king999",
    "likes": 1,
    "time": 1755278328,
    "date": "2025-08-15 17:18:48",
    "video_id": "2b6Jr6YKKLo",
    "is_reply": false,
    "extraction_method": "youtube_api",
    "sentiment": "negative",
    "sentiment_score": 0.4596508741378784,
    "oem": "Ola Electric",
    "month": "2025-01"
  },
  {
    "text": "Ola kharidne Se pahle service centre mein jaaiye vah ola scooty owners ka taklif dekhiae no service centre \nResponsibility \nNo mileage garantee \n42%. Or 36% to 😢1% drop battery \n\nSpare parts high costly \nNo skill workers\nNo charging stations",
    "author": "@srinivasachary997",
    "likes": 13,
    "time": 1755277402,
    "date": "2025-08-15 17:03:22",
    "video_id": "2b6Jr6YKKLo",
    "is_reply": false,
    "extraction_method": "youtube_api",
    "sentiment": "negative",
    "sentiment_score": 0.6140612363815308,
    "oem": "Ola Electric",
    "month": "2025-01"
  },
  {
    "text": "Ola roadster 4.5 kab aaygi koi fix date aaye",
    "author": "@JAVEDANSARI-mw2qd",
    "likes": 1,
    "time": 1755276974,
    "date": "2025-08-15 16:56:14",
    "video_id": "2b6Jr6YKKLo",
    "is_reply": false,
    "extraction_method": "youtube_api",
    "sentiment": "neutral",
    "sentiment_score": 0.4979204833507538,
    "oem": "Ola Electric",
    "month": "2025-01"
  },
  {
    "text": "Ola is best",
    "author": "@ajaykalokhe9596",
    "likes": 0,
    "time": 1755276689,
    "date": "2025-08-15 16:51:29",
    "video_id": "2b6Jr6YKKLo",
    "is_reply": false,
    "extraction_method": "youtube_api",
    "sentiment": "positive",
    "sentiment_score": 0.6890122294425964,
    "oem": "Ola Electric",
    "month": "2025-01"
  },
  {
    "text": "😳are roadstar ka keya hua",
    "author": "@pabitrasamanta5513",
    "likes": 1,
    "time": 1755276450,
    "date": "2025-08-15 16:47:30",
    "video_id": "2b6Jr6YKKLo",
    "is_reply": false,
    "extraction_method": "youtube_api",
    "sentiment": "neutral",
    "sentiment_score": 0.4198785424232483,
    "oem": "Ola Electric",
    "month": "2025-01"
  },
  {
    "text": "Don't buy ola",
    "author": "@ridethefuture01",
    "likes": 1,
    "time": 1755274846,
    "date": "2025-08-15 16:20:46",
    "video_id": "2b6Jr6YKKLo",
    "is_reply": false,
    "extraction_method": "youtube_api",
    "sentiment": "negative",
    "sentiment_score": 0.6367027759552002,
    "oem": "Ola Electric",
    "month": "2025-01"
  },
  {
    "text": "Itne me koi samjhdar hi lega ise",
    "author": "@krdeepak1129",
    "likes": 0,
    "time": 1755274508,
    "date": "2025-08-15 16:15:08",
    "video_id": "2b6Jr6YKKLo",
    "is_reply": false,
    "extraction_method": "youtube_api",
    "sentiment": "negative",
    "sentiment_score": 0.338377982378006,
    "oem": "Ola Electric",
    "month": "2025-01"
  },
  {
    "text": "Ola scooter is really a scam, my scooter is on road with 10 others, its about 2 months passed 😢",
    "author": "@nirmalable1",
    "likes": 2,
    "time": 1755274110,
    "date": "2025-08-15 16:08:30",
    "video_id": "2b6Jr6YKKLo",
    "is_reply": false,
    "extraction_method": "youtube_api",
    "sentiment": "negative",
    "sentiment_score": 0.9208042025566101,
    "oem": "Ola Electric",
    "month": "2025-01"
  },
  {
    "text": "I booked Ola  S1 pro plus 5.4 kwh on Feb 2025,still no news of its delivery.",
    "author": "@nibeditabiswas2170",
    "likes": 0,
    "time": 1755273563,
    "date": "2025-08-15 15:59:23",
    "video_id": "2b6Jr6YKKLo",
    "is_reply": false,
    "extraction_method": "youtube_api",
    "sentiment": "neutral",
    "sentiment_score": 0.8449075222015381,
    "oem": "Ola Electric",
    "month": "2025-01"
  },
  {
    "text": "Roadster & Roadster Pro updates still pending... Ola claims Diamond Head will arrive in 2027\n\n#ola❌❌❌\nit's #olaceobhavishaggarwal Hawa Baji company",
    "author": "@legendalpha4352",
    "likes": 1,
    "time": 1755273504,
    "date": "2025-08-15 15:58:24",
    "video_id": "2b6Jr6YKKLo",
    "is_reply": false,
    "extraction_method": "youtube_api",
    "sentiment": "neutral",
    "sentiment_score": 0.5702831745147705,
    "oem": "Ola Electric",
    "month": "2025-01"
  },
  {
    "text": "No one will buy it .. the way these guys have service in place",
    "author": "@kiranm6749",
    "likes": 3,
    "time": 1755273322,
    "date": "2025-08-15 15:55:22",
    "video_id": "2b6Jr6YKKLo",
    "is_reply": false,
    "extraction_method": "youtube_api",
    "sentiment": "negative",
    "sentiment_score": 0.47467368841171265,
    "oem": "Ola Electric",
    "month": "2025-01"
  },
  {
    "text": "Bhai Roadster ka toh kuch ata pata hi nahi chala...",
    "author": "@unknownartist41",
    "likes": 6,
    "time": 1755273065,
    "date": "2025-08-15 15:51:05",
    "video_id": "2b6Jr6YKKLo",
    "is_reply": false,
    "extraction_method": "youtube_api",
    "sentiment": "negative",
    "sentiment_score": 0.39086204767227173,
    "oem": "Ola Electric",
    "month": "2025-01"
  },
  {
    "text": "Sport scotty mein kuch changes nahi hai sirf side panel aur kuch grab handle modify almost same",
    "author": "@Rabindra-dp3rc2xi7x",
    "likes": 1,
    "time": 1755272581,
    "date": "2025-08-15 15:43:01",
    "video_id": "2b6Jr6YKKLo",
    "is_reply": false,
    "extraction_method": "youtube_api",
    "sentiment": "neutral",
    "sentiment_score": 0.5098285675048828,
    "oem": "Ola Electric",
    "month": "2025-01"
  },
  {
    "text": "Ola ka gola banne bala hai future in hydrogen based vehicle",
    "author": "@miniyuvraj",
    "likes": 1,
    "time": 1755271940,
    "date": "2025-08-15 15:32:20",
    "video_id": "2b6Jr6YKKLo",
    "is_reply": false,
    "extraction_method": "youtube_api",
    "sentiment": "neutral",
    "sentiment_score": 0.4193177819252014,
    "oem": "Ola Electric",
    "month": "2025-01"
  },
  {
    "text": "Sabse kachra gadi😂😂😂😂",
    "author": "@ShailendraKumar-cj8uo",
    "likes": 4,
    "time": 1755271883,
    "date": "2025-08-15 15:31:23",
    "video_id": "2b6Jr6YKKLo",
    "is_reply": false,
    "extraction_method": "youtube_api",
    "sentiment": "negative",
    "sentiment_score": 0.37591755390167236,
    "oem": "Ola Electric",
    "month": "2025-01"
  },
  {
    "text": "Are bhai ola ki kwalitiy aur service third class hai",
    "author": "@miniyuvraj",
    "likes": 2,
    "time": 1755271823,
    "date": "2025-08-15 15:30:23",
    "video_id": "2b6Jr6YKKLo",
    "is_reply": false,
    "extraction_method": "youtube_api",
    "sentiment": "neutral",
    "sentiment_score": 0.3455265462398529,
    "oem": "Ola Electric",
    "month": "2025-01"
  },
  {
    "text": "Service better korne bolo",
    "author": "@biswameditation7694",
    "likes": 1,
    "time": 1755271520,
    "date": "2025-08-15 15:25:20",
    "video_id": "2b6Jr6YKKLo",
    "is_reply": false,
    "extraction_method": "youtube_api",
    "sentiment": "negative",
    "sentiment_score": 0.3507237732410431,
    "oem": "Ola Electric",
    "month": "2025-01"
  },
  {
    "text": "Ola aur modi k bhashan par sirf andbhakht bharosa karengein ...😂",
    "author": "@soheb10",
    "likes": 1,
    "time": 1755271490,
    "date": "2025-08-15 15:24:50",
    "video_id": "2b6Jr6YKKLo",
    "is_reply": false,
    "extraction_method": "youtube_api",
    "sentiment": "negative",
    "sentiment_score": 0.3876302242279053,
    "oem": "Ola Electric",
    "month": "2025-01"
  },
  {
    "text": "Maine ola S1 Pro Plus 5.3 kwh variant order kiya tha ab mere ko vah cancel karke preorder karna padega to cancel kaise karunga",
    "author": "@manjeetsingh-yp7ev",
    "likes": 0,
    "time": 1755271434,
    "date": "2025-08-15 15:23:54",
    "video_id": "2b6Jr6YKKLo",
    "is_reply": false,
    "extraction_method": "youtube_api",
    "sentiment": "neutral",
    "sentiment_score": 0.3811816871166229,
    "oem": "Ola Electric",
    "month": "2025-01"
  },
  {
    "text": "Roadster x+4.5 Le kar Roooo raha hoo bahut ghatiya gadi hai 35 din me 22 din service center me hai.",
    "author": "@kameshwarsinha2515",
    "likes": 13,
    "time": 1755271362,
    "date": "2025-08-15 15:22:42",
    "video_id": "2b6Jr6YKKLo",
    "is_reply": false,
    "extraction_method": "youtube_api",
    "sentiment": "negative",
    "sentiment_score": 0.3591160774230957,
    "oem": "Ola Electric",
    "month": "2025-01"
  },
  {
    "text": "Sir inka delevery status ab app me show nahi ho raha hai",
    "author": "@pradiptervankar5850",
    "likes": 1,
    "time": 1755271314,
    "date": "2025-08-15 15:21:54",
    "video_id": "2b6Jr6YKKLo",
    "is_reply": false,
    "extraction_method": "youtube_api",
    "sentiment": "negative",
    "sentiment_score": 0.4096248745918274,
    "oem": "Ola Electric",
    "month": "2025-01"
  },
  {
    "text": "Ola Bad Service please improve service",
    "author": "@gohilsuresh2017",
    "likes": 1,
    "time": 1755271041,
    "date": "2025-08-15 15:17:21",
    "video_id": "2b6Jr6YKKLo",
    "is_reply": false,
    "extraction_method": "youtube_api",
    "sentiment": "negative",
    "sentiment_score": 0.7522071003913879,
    "oem": "Ola Electric",
    "month": "2025-01"
  },
  {
    "text": "320km nahi..160 km hi milegi 😂",
    "author": "@SarthakSuneja-n2i",
    "likes": 2,
    "time": 1755270766,
    "date": "2025-08-15 15:12:46",
    "video_id": "2b6Jr6YKKLo",
    "is_reply": false,
    "extraction_method": "youtube_api",
    "sentiment": "neutral",
    "sentiment_score": 0.45135486125946045,
    "oem": "Ola Electric",
    "month": "2025-01"
  },
  {
    "text": "Ola service is very bad, don't buy, no propper response from the company side",
    "author": "@ranjitgupta7376",
    "likes": 13,
    "time": 1755269844,
    "date": "2025-08-15 14:57:24",
    "video_id": "2b6Jr6YKKLo",
    "is_reply": false,
    "extraction_method": "youtube_api",
    "sentiment": "negative",
    "sentiment_score": 0.9370864033699036,
    "oem": "Ola Electric",
    "month": "2025-01"
  },
  {
    "text": "Offering offers only till purchase and after purchase every facilities are taking back and we should pay back to get already available services",
    "author": "@sayoojk.k2931",
    "likes": 0,
    "time": 1755269756,
    "date": "2025-08-15 14:55:56",
    "video_id": "2b6Jr6YKKLo",
    "is_reply": false,
    "extraction_method": "youtube_api",
    "sentiment": "neutral",
    "sentiment_score": 0.7625578045845032,
    "oem": "Ola Electric",
    "month": "2025-01"
  },
  {
    "text": "Dont purchase ola vehicle.... Fraud company making fool of customers.... No service available, no customer care no use.....",
    "author": "@sayoojk.k2931",
    "likes": 0,
    "time": 1755269681,
    "date": "2025-08-15 14:54:41",
    "video_id": "2b6Jr6YKKLo",
    "is_reply": false,
    "extraction_method": "youtube_api",
    "sentiment": "negative",
    "sentiment_score": 0.9237882494926453,
    "oem": "Ola Electric",
    "month": "2025-01"
  },
  {
    "text": "ओला का सच भी झूठ लगता है😂",
    "author": "@uttamdewangan2847",
    "likes": 2,
    "time": 1755269574,
    "date": "2025-08-15 14:52:54",
    "video_id": "2b6Jr6YKKLo",
    "is_reply": false,
    "extraction_method": "youtube_api",
    "sentiment": "negative",
    "sentiment_score": 0.6206619739532471,
    "oem": "Ola Electric",
    "month": "2025-01"
  },
  {
    "text": "Service very bad",
    "author": "@sayoojk.k2931",
    "likes": 0,
    "time": 1755269508,
    "date": "2025-08-15 14:51:48",
    "video_id": "2b6Jr6YKKLo",
    "is_reply": false,
    "extraction_method": "youtube_api",
    "sentiment": "negative",
    "sentiment_score": 0.9368129372596741,
    "oem": "Ola Electric",
    "month": "2025-01"
  },
  {
    "text": "Sport Book Kar Rha Hu Kal",
    "author": "@ssjonly",
    "likes": 1,
    "time": 1755269422,
    "date": "2025-08-15 14:50:22",
    "video_id": "2b6Jr6YKKLo",
    "is_reply": false,
    "extraction_method": "youtube_api",
    "sentiment": "neutral",
    "sentiment_score": 0.4723685085773468,
    "oem": "Ola Electric",
    "month": "2025-01"
  },
  {
    "text": "https://youtube.com/shorts/XzY151CpLC4?si=tqqS2SLBetoTR5o6😢😢😢😢😢they all are making you fool",
    "author": "@advait-p4t",
    "likes": 0,
    "time": 1755268837,
    "date": "2025-08-15 14:40:37",
    "video_id": "2b6Jr6YKKLo",
    "is_reply": false,
    "extraction_method": "youtube_api",
    "sentiment": "negative",
    "sentiment_score": 0.7689147591590881,
    "oem": "Ola Electric",
    "month": "2025-01"
  },
  {
    "text": "Bhai aaj dil tut gaya roadster ka intezar tha socha tha aaj roadster launch hogi par nhi hui intezar krte krte ab sabra bhi khtm ho gya ab uski jegah kiya khridu kuch samajh nhi aa rha sab blank sa ho gya hai",
    "author": "@MsNitin94",
    "likes": 7,
    "time": 1755267579,
    "date": "2025-08-15 14:19:39",
    "video_id": "2b6Jr6YKKLo",
    "is_reply": false,
    "extraction_method": "youtube_api",
    "sentiment": "negative",
    "sentiment_score": 0.4078576862812042,
    "oem": "Ola Electric",
    "month": "2025-01"
  },
  {
    "text": "petrol scooter is good one🎉🎉",
    "author": "@rs.0-v2x",
    "likes": 6,
    "time": 1755267101,
    "date": "2025-08-15 14:11:41",
    "video_id": "2b6Jr6YKKLo",
    "is_reply": false,
    "extraction_method": "youtube_api",
    "sentiment": "positive",
    "sentiment_score": 0.8979985117912292,
    "oem": "Ola Electric",
    "month": "2025-01"
  },
  {
    "text": "ओला मत लेना😢😢😢",
    "author": "@nitinghatage2852",
    "likes": 3,
    "time": 1755266794,
    "date": "2025-08-15 14:06:34",
    "video_id": "2b6Jr6YKKLo",
    "is_reply": false,
    "extraction_method": "youtube_api",
    "sentiment": "negative",
    "sentiment_score": 0.8248482942581177,
    "oem": "Ola Electric",
    "month": "2025-01"
  },
  {
    "text": "I was waiting for Roadster 6kwh 😢",
    "author": "@vishalsahu1981",
    "likes": 5,
    "time": 1755266767,
    "date": "2025-08-15 14:06:07",
    "video_id": "2b6Jr6YKKLo",
    "is_reply": false,
    "extraction_method": "youtube_api",
    "sentiment": "negative",
    "sentiment_score": 0.7314832806587219,
    "oem": "Ola Electric",
    "month": "2025-01"
  },
  {
    "text": "Roadster ka kya hua sir\n\nWe have booked and Waiting for long period",
    "author": "@ssbofficial3542",
    "likes": 2,
    "time": 1755266064,
    "date": "2025-08-15 13:54:24",
    "video_id": "2b6Jr6YKKLo",
    "is_reply": false,
    "extraction_method": "youtube_api",
    "sentiment": "neutral",
    "sentiment_score": 0.48301029205322266,
    "oem": "Ola Electric",
    "month": "2025-01"
  },
  {
    "text": "😍😍😍🤩",
    "author": "@TARGETGOVTJOB25",
    "likes": 0,
    "time": 1755265962,
    "date": "2025-08-15 13:52:42",
    "video_id": "2b6Jr6YKKLo",
    "is_reply": false,
    "extraction_method": "youtube_api",
    "sentiment": "positive",
    "sentiment_score": 0.7875981330871582,
    "oem": "Ola Electric",
    "month": "2025-01"
  },
  {
    "text": "Big fan sir please pin \n1st view",
    "author": "@ankitchaturvedi02",
    "likes": 15,
    "time": 1738399510,
    "date": "2025-02-01 08:45:10",
    "video_id": "mIHzEZfB334",
    "is_reply": false,
    "extraction_method": "youtube_api",
    "sentiment": "positive",
    "sentiment_score": 0.46365270018577576,
    "oem": "Ola Electric",
    "month": "2025-01"
  },
  {
    "text": "Ur information is on topppp sir ❤\n Sir ola s1 pro gen 3 5.3 leu kya",
    "author": "@rockstarrockstar1661",
    "likes": 1,
    "time": 1739267158,
    "date": "2025-02-11 09:45:58",
    "video_id": "mIHzEZfB334",
    "is_reply": false,
    "extraction_method": "youtube_api",
    "sentiment": "positive",
    "sentiment_score": 0.5859197378158569,
    "oem": "Ola Electric",
    "month": "2025-01"
  },
  {
    "text": "Bajaj chetak ki customer service bahut bear h",
    "author": "@dheerajkumar3594",
    "likes": 0,
    "time": 1739035792,
    "date": "2025-02-08 17:29:52",
    "video_id": "mIHzEZfB334",
    "is_reply": false,
    "extraction_method": "youtube_api",
    "sentiment": "negative",
    "sentiment_score": 0.43506208062171936,
    "oem": "Ola Electric",
    "month": "2025-01"
  },
  {
    "text": "मैंने टीवीएस का ₹100000 से ज्यादा मूल्य का बैटरी वाला टू व्हीलर खरीदा था। \n35 से 40000 किलोमीटर चलने के बाद उसकी बैटरी खराब हो गई।\nपरंतु 50000 किलोमीटर तक की गारंटी मिली थी फिर भी टीवीएस कंपनी ने उसकी बैट्री रिप्लेसमेंट नहीं की।\nबाद में उसे चलाने के लिए 40 से ₹50000 की नई बैटरी की जरूरत थी।\nफिर उसको कबाड़ में बेचना पड़ा और मुझे ₹9000 मिला।",
    "author": "@kunalsingla5671",
    "likes": 2,
    "time": 1738789937,
    "date": "2025-02-05 21:12:17",
    "video_id": "mIHzEZfB334",
    "is_reply": false,
    "extraction_method": "youtube_api",
    "sentiment": "neutral",
    "sentiment_score": 0.4499620199203491,
    "oem": "Ola Electric",
    "month": "2025-01"
  },
  {
    "text": "EV car या  दो पहिया वाहन खरीदने वाला ग्राहक बिल्कुल भी तजुर्बे कर नहीं होता है।\nEV  दो पहिया वाहन या कार की बैट्री रिप्लेसमेंट का खर्च उसके पेट्रोल या डीजल से कहीं ज्यादा होता है।",
    "author": "@kunalsingla5671",
    "likes": 0,
    "time": 1738789926,
    "date": "2025-02-05 21:12:06",
    "video_id": "mIHzEZfB334",
    "is_reply": false,
    "extraction_method": "youtube_api",
    "sentiment": "neutral",
    "sentiment_score": 0.49092456698417664,
    "oem": "Ola Electric",
    "month": "2025-01"
  },
  {
    "text": "Ola gen3 chain cover meterial ?",
    "author": "@mayankgupta1410",
    "likes": 0,
    "time": 1738754762,
    "date": "2025-02-05 11:26:02",
    "video_id": "mIHzEZfB334",
    "is_reply": false,
    "extraction_method": "youtube_api",
    "sentiment": "neutral",
    "sentiment_score": 0.8635517358779907,
    "oem": "Ola Electric",
    "month": "2025-01"
  },
  {
    "text": "E scooter ka review apke channel pe hi satisfaction hoti h❤",
    "author": "@Sohel_akhtar_001",
    "likes": 0,
    "time": 1738566273,
    "date": "2025-02-03 07:04:33",
    "video_id": "mIHzEZfB334",
    "is_reply": false,
    "extraction_method": "youtube_api",
    "sentiment": "positive",
    "sentiment_score": 0.49099108576774597,
    "oem": "Ola Electric",
    "month": "2025-01"
  },
  {
    "text": "Ola giving fake range 5 kwh battery 300 km range. \nTvs, simple one 5 kwh battery 160 around range",
    "author": "@AbdulSattar-dd5yw",
    "likes": 0,
    "time": 1738522855,
    "date": "2025-02-02 19:00:55",
    "video_id": "mIHzEZfB334",
    "is_reply": false,
    "extraction_method": "youtube_api",
    "sentiment": "neutral",
    "sentiment_score": 0.772585391998291,
    "oem": "Ola Electric",
    "month": "2025-01"
  },
  {
    "text": "I bought Chetak 2903 in January",
    "author": "@h.s.opshorts5630",
    "likes": 0,
    "time": 1738497833,
    "date": "2025-02-02 12:03:53",
    "video_id": "mIHzEZfB334",
    "is_reply": false,
    "extraction_method": "youtube_api",
    "sentiment": "neutral",
    "sentiment_score": 0.8194543123245239,
    "oem": "Ola Electric",
    "month": "2025-01"
  },
  {
    "text": "Gen 3 x4kw vs x4kw+ ka video bnao",
    "author": "@Yash_Enterprises_bhopal",
    "likes": 0,
    "time": 1738491841,
    "date": "2025-02-02 10:24:01",
    "video_id": "mIHzEZfB334",
    "is_reply": false,
    "extraction_method": "youtube_api",
    "sentiment": "neutral",
    "sentiment_score": 0.744266927242279,
    "oem": "Ola Electric",
    "month": "2025-01"
  },
  {
    "text": "Sir 50 - 70k bich koi achi ev bata do",
    "author": "@VEDVRATTiwari-z8m",
    "likes": 1,
    "time": 1738481030,
    "date": "2025-02-02 07:23:50",
    "video_id": "mIHzEZfB334",
    "is_reply": false,
    "extraction_method": "youtube_api",
    "sentiment": "neutral",
    "sentiment_score": 0.4136655032634735,
    "oem": "Ola Electric",
    "month": "2025-01"
  },
  {
    "text": "Maine chetal 3501 book kr liya he , decision sahi liya na?",
    "author": "@sadhucharansoy813",
    "likes": 1,
    "time": 1738472306,
    "date": "2025-02-02 04:58:26",
    "video_id": "mIHzEZfB334",
    "is_reply": false,
    "extraction_method": "youtube_api",
    "sentiment": "neutral",
    "sentiment_score": 0.38702091574668884,
    "oem": "Ola Electric",
    "month": "2025-01"
  },
  {
    "text": "Ab to jada poisa deke Balaji tvs lene ka fsida k hay",
    "author": "@শুভঙ্করবিশ্বাস-ভ৮শ",
    "likes": 0,
    "time": 1738471372,
    "date": "2025-02-02 04:42:52",
    "video_id": "mIHzEZfB334",
    "is_reply": false,
    "extraction_method": "youtube_api",
    "sentiment": "negative",
    "sentiment_score": 0.34894949197769165,
    "oem": "Ola Electric",
    "month": "2025-01"
  },
  {
    "text": "Aap must video banate ho Big fan hu aapka ❤❤❤❤",
    "author": "@Jeet_video_edits",
    "likes": 0,
    "time": 1738469298,
    "date": "2025-02-02 04:08:18",
    "video_id": "mIHzEZfB334",
    "is_reply": false,
    "extraction_method": "youtube_api",
    "sentiment": "positive",
    "sentiment_score": 0.6615936756134033,
    "oem": "Ola Electric",
    "month": "2025-01"
  },
  {
    "text": "Service of ola should be next generation, and updated",
    "author": "@Shivakumar-hl3hr",
    "likes": 3,
    "time": 1738468252,
    "date": "2025-02-02 03:50:52",
    "video_id": "mIHzEZfB334",
    "is_reply": false,
    "extraction_method": "youtube_api",
    "sentiment": "neutral",
    "sentiment_score": 0.5219079256057739,
    "oem": "Ola Electric",
    "month": "2025-01"
  },
  {
    "text": "Supper information tq",
    "author": "@SureshGowdaa",
    "likes": 1,
    "time": 1738435120,
    "date": "2025-02-01 18:38:40",
    "video_id": "mIHzEZfB334",
    "is_reply": false,
    "extraction_method": "youtube_api",
    "sentiment": "neutral",
    "sentiment_score": 0.48703059554100037,
    "oem": "Ola Electric",
    "month": "2025-01"
  },
  {
    "text": "https://youtu.be/IBoGutQVraY?si=CTNn3Upxo_avfUfn",
    "author": "@hariomtawlare4656",
    "likes": 0,
    "time": 1738434654,
    "date": "2025-02-01 18:30:54",
    "video_id": "mIHzEZfB334",
    "is_reply": false,
    "extraction_method": "youtube_api",
    "sentiment": "neutral",
    "sentiment_score": 0.7461090683937073,
    "oem": "Ola Electric",
    "month": "2025-01"
  },
  {
    "text": "Ola me konsa variant best rahega \nMe ye month lene ja raha hu plz suggest best ev scooter",
    "author": "@nikrathod95",
    "likes": 0,
    "time": 1738432723,
    "date": "2025-02-01 17:58:43",
    "video_id": "mIHzEZfB334",
    "is_reply": false,
    "extraction_method": "youtube_api",
    "sentiment": "neutral",
    "sentiment_score": 0.4216223359107971,
    "oem": "Ola Electric",
    "month": "2025-01"
  },
  {
    "text": "Ola op",
    "author": "@ST_BOOS_RH25",
    "likes": 0,
    "time": 1738431567,
    "date": "2025-02-01 17:39:27",
    "video_id": "mIHzEZfB334",
    "is_reply": false,
    "extraction_method": "youtube_api",
    "sentiment": "neutral",
    "sentiment_score": 0.4518132507801056,
    "oem": "Ola Electric",
    "month": "2025-01"
  },
  {
    "text": "Ola performance peak level ❤",
    "author": "@ramanjanappaky9566",
    "likes": 1,
    "time": 1738431047,
    "date": "2025-02-01 17:30:47",
    "video_id": "mIHzEZfB334",
    "is_reply": false,
    "extraction_method": "youtube_api",
    "sentiment": "positive",
    "sentiment_score": 0.8511471748352051,
    "oem": "Ola Electric",
    "month": "2025-01"
  },
  {
    "text": "we are purchasing \"ola roadster x \" on February itself... 4.5kw wala",
    "author": "@GuruprasadHiremath-wj5hy",
    "likes": 0,
    "time": 1738430830,
    "date": "2025-02-01 17:27:10",
    "video_id": "mIHzEZfB334",
    "is_reply": false,
    "extraction_method": "youtube_api",
    "sentiment": "neutral",
    "sentiment_score": 0.7847755551338196,
    "oem": "Ola Electric",
    "month": "2025-01"
  },
  {
    "text": "Ola top pe thi hai aur rhegi",
    "author": "@Cahnijnatlui",
    "likes": 0,
    "time": 1738430711,
    "date": "2025-02-01 17:25:11",
    "video_id": "mIHzEZfB334",
    "is_reply": false,
    "extraction_method": "youtube_api",
    "sentiment": "positive",
    "sentiment_score": 0.37899744510650635,
    "oem": "Ola Electric",
    "month": "2025-01"
  },
  {
    "text": "Bajaj Chetak ❤",
    "author": "@attaraslamj",
    "likes": 2,
    "time": 1738428727,
    "date": "2025-02-01 16:52:07",
    "video_id": "mIHzEZfB334",
    "is_reply": false,
    "extraction_method": "youtube_api",
    "sentiment": "neutral",
    "sentiment_score": 0.5518682599067688,
    "oem": "Ola Electric",
    "month": "2025-01"
  },
  {
    "text": "13 jan ( chetak 2903 ) \nSuggestion ( do not buy )",
    "author": "@Shivam-p4i-c7f",
    "likes": 0,
    "time": 1738425451,
    "date": "2025-02-01 15:57:31",
    "video_id": "mIHzEZfB334",
    "is_reply": false,
    "extraction_method": "youtube_api",
    "sentiment": "neutral",
    "sentiment_score": 0.6541553139686584,
    "oem": "Ola Electric",
    "month": "2025-01"
  },
  {
    "text": "Ola ka gen3 kab Se booking Chalu hoga???",
    "author": "@TechnicalSupport202",
    "likes": 1,
    "time": 1738425194,
    "date": "2025-02-01 15:53:14",
    "video_id": "mIHzEZfB334",
    "is_reply": false,
    "extraction_method": "youtube_api",
    "sentiment": "neutral",
    "sentiment_score": 0.5505428910255432,
    "oem": "Ola Electric",
    "month": "2025-01"
  },
  {
    "text": "Vida V2 plz charging point lagao apne showroom k bahar",
    "author": "@sukhma1321",
    "likes": 0,
    "time": 1738424924,
    "date": "2025-02-01 15:48:44",
    "video_id": "mIHzEZfB334",
    "is_reply": false,
    "extraction_method": "youtube_api",
    "sentiment": "neutral",
    "sentiment_score": 0.42662274837493896,
    "oem": "Ola Electric",
    "month": "2025-01"
  },
  {
    "text": "I am one of the ola bike owners, The service was a bit improved compared to the previous year.",
    "author": "@gopayyanaidu6597",
    "likes": 2,
    "time": 1738423518,
    "date": "2025-02-01 15:25:18",
    "video_id": "mIHzEZfB334",
    "is_reply": false,
    "extraction_method": "youtube_api",
    "sentiment": "positive",
    "sentiment_score": 0.8070845007896423,
    "oem": "Ola Electric",
    "month": "2025-01"
  },
  {
    "text": "My heartly wishes to ola ola is best",
    "author": "@shrikantdixit726",
    "likes": 1,
    "time": 1738423196,
    "date": "2025-02-01 15:19:56",
    "video_id": "mIHzEZfB334",
    "is_reply": false,
    "extraction_method": "youtube_api",
    "sentiment": "positive",
    "sentiment_score": 0.7442008256912231,
    "oem": "Ola Electric",
    "month": "2025-01"
  },
  {
    "text": "Top notch services by ola now",
    "author": "@space-berg3820",
    "likes": 3,
    "time": 1738422688,
    "date": "2025-02-01 15:11:28",
    "video_id": "mIHzEZfB334",
    "is_reply": false,
    "extraction_method": "youtube_api",
    "sentiment": "positive",
    "sentiment_score": 0.8081686496734619,
    "oem": "Ola Electric",
    "month": "2025-01"
  },
  {
    "text": "Ola gadha ka l...",
    "author": "@AbhishekdauDau",
    "likes": 0,
    "time": 1738416416,
    "date": "2025-02-01 13:26:56",
    "video_id": "mIHzEZfB334",
    "is_reply": false,
    "extraction_method": "youtube_api",
    "sentiment": "positive",
    "sentiment_score": 0.3752738833427429,
    "oem": "Ola Electric",
    "month": "2025-01"
  },
  {
    "text": "this bro is biggest OLA fan on the whole of internet 😂😂😅",
    "author": "@ARNABOSS",
    "likes": 2,
    "time": 1738414944,
    "date": "2025-02-01 13:02:24",
    "video_id": "mIHzEZfB334",
    "is_reply": false,
    "extraction_method": "youtube_api",
    "sentiment": "positive",
    "sentiment_score": 0.5407162308692932,
    "oem": "Ola Electric",
    "month": "2025-01"
  },
  {
    "text": "Bajaj chetak",
    "author": "@niketankasundra4785",
    "likes": 2,
    "time": 1738414011,
    "date": "2025-02-01 12:46:51",
    "video_id": "mIHzEZfB334",
    "is_reply": false,
    "extraction_method": "youtube_api",
    "sentiment": "neutral",
    "sentiment_score": 0.46131888031959534,
    "oem": "Ola Electric",
    "month": "2025-01"
  },
  {
    "text": "VALUE FOR MONEY AND FEATURE HEN ITS OLA... QUALITY AND FEATURES ITS ATHER",
    "author": "@nallenthiran2720",
    "likes": 1,
    "time": 1738413952,
    "date": "2025-02-01 12:45:52",
    "video_id": "mIHzEZfB334",
    "is_reply": false,
    "extraction_method": "youtube_api",
    "sentiment": "neutral",
    "sentiment_score": 0.5280611515045166,
    "oem": "Ola Electric",
    "month": "2025-01"
  },
  {
    "text": "Mere ko ola S1 pro purchase karna he ..me gen 2 lu ya gen 3..gen 2 pr 20000rs ki bachat ho rahi he..mere leye kya sahi rahega",
    "author": "@praveenprajapati284",
    "likes": 1,
    "time": 1738412649,
    "date": "2025-02-01 12:24:09",
    "video_id": "mIHzEZfB334",
    "is_reply": false,
    "extraction_method": "youtube_api",
    "sentiment": "neutral",
    "sentiment_score": 0.3756941258907318,
    "oem": "Ola Electric",
    "month": "2025-01"
  },
  {
    "text": "Service improve hai h",
    "author": "@SanjayYadav-db6iu",
    "likes": 1,
    "time": 1738410751,
    "date": "2025-02-01 11:52:31",
    "video_id": "mIHzEZfB334",
    "is_reply": false,
    "extraction_method": "youtube_api",
    "sentiment": "positive",
    "sentiment_score": 0.44108420610427856,
    "oem": "Ola Electric",
    "month": "2025-01"
  },
  {
    "text": "Bajaj launching new product and they dropped 1st to 3rd hehe. After ola gen 3 top crown will be distant dream for some time",
    "author": "@kirantarafder.allthingseasyy",
    "likes": 0,
    "time": 1738409853,
    "date": "2025-02-01 11:37:33",
    "video_id": "mIHzEZfB334",
    "is_reply": false,
    "extraction_method": "youtube_api",
    "sentiment": "positive",
    "sentiment_score": 0.7125453352928162,
    "oem": "Ola Electric",
    "month": "2025-01"
  },
  {
    "text": "Bhai ajmer se ho ky",
    "author": "@SorabhPanchal051",
    "likes": 1,
    "time": 1738409364,
    "date": "2025-02-01 11:29:24",
    "video_id": "mIHzEZfB334",
    "is_reply": false,
    "extraction_method": "youtube_api",
    "sentiment": "negative",
    "sentiment_score": 0.3736725151538849,
    "oem": "Ola Electric",
    "month": "2025-01"
  },
  {
    "text": "I am buying Vida V२ plus",
    "author": "@nimbalkarsushil",
    "likes": 2,
    "time": 1738409268,
    "date": "2025-02-01 11:27:48",
    "video_id": "mIHzEZfB334",
    "is_reply": false,
    "extraction_method": "youtube_api",
    "sentiment": "neutral",
    "sentiment_score": 0.7982332706451416,
    "oem": "Ola Electric",
    "month": "2025-01"
  },
  {
    "text": "Chetak available hi nahi hai sab jagh mere yahan abhi tak 2903 hi bech rahe hai.",
    "author": "@My_words75",
    "likes": 2,
    "time": 1738407794,
    "date": "2025-02-01 11:03:14",
    "video_id": "mIHzEZfB334",
    "is_reply": false,
    "extraction_method": "youtube_api",
    "sentiment": "negative",
    "sentiment_score": 0.4256121516227722,
    "oem": "Ola Electric",
    "month": "2025-01"
  },
  {
    "text": "Good service",
    "author": "@TCSinformation",
    "likes": 1,
    "time": 1738407644,
    "date": "2025-02-01 11:00:44",
    "video_id": "mIHzEZfB334",
    "is_reply": false,
    "extraction_method": "youtube_api",
    "sentiment": "positive",
    "sentiment_score": 0.6970433592796326,
    "oem": "Ola Electric",
    "month": "2025-01"
  },
  {
    "text": "BHAI ROADSTER KE UPAR KUCH VDO BANAO",
    "author": "@GBM-zairoff-live",
    "likes": 2,
    "time": 1738406968,
    "date": "2025-02-01 10:49:28",
    "video_id": "mIHzEZfB334",
    "is_reply": false,
    "extraction_method": "youtube_api",
    "sentiment": "negative",
    "sentiment_score": 0.4629906415939331,
    "oem": "Ola Electric",
    "month": "2025-01"
  },
  {
    "text": "River indie underrated one🔥",
    "author": "@fasalpm1522",
    "likes": 3,
    "time": 1738406676,
    "date": "2025-02-01 10:44:36",
    "video_id": "mIHzEZfB334",
    "is_reply": false,
    "extraction_method": "youtube_api",
    "sentiment": "positive",
    "sentiment_score": 0.9055232405662537,
    "oem": "Ola Electric",
    "month": "2025-01"
  },
  {
    "text": "the most value for money is chetak because of the built quality and new chetak average is same as base model  that is 153 km range .",
    "author": "@MohdSiraj-z3u",
    "likes": 2,
    "time": 1738404897,
    "date": "2025-02-01 10:14:57",
    "video_id": "mIHzEZfB334",
    "is_reply": false,
    "extraction_method": "youtube_api",
    "sentiment": "positive",
    "sentiment_score": 0.4807930588722229,
    "oem": "Ola Electric",
    "month": "2025-01"
  },
  {
    "text": "Ola is best ...value for money product....using since 2 and half years",
    "author": "@AMOLPATIL-wh3dm",
    "likes": 5,
    "time": 1738404723,
    "date": "2025-02-01 10:12:03",
    "video_id": "mIHzEZfB334",
    "is_reply": false,
    "extraction_method": "youtube_api",
    "sentiment": "positive",
    "sentiment_score": 0.779486358165741,
    "oem": "Ola Electric",
    "month": "2025-01"
  },
  {
    "text": "Gen3 ka ditel video banao",
    "author": "@topsongedit",
    "likes": 5,
    "time": 1738404370,
    "date": "2025-02-01 10:06:10",
    "video_id": "mIHzEZfB334",
    "is_reply": false,
    "extraction_method": "youtube_api",
    "sentiment": "neutral",
    "sentiment_score": 0.41071978211402893,
    "oem": "Ola Electric",
    "month": "2025-01"
  },
  {
    "text": "But 1.76 me hunter 350 ka base varient ata hai aur s1 pro ka top varient 1.86 me ata hai.",
    "author": "@RachitTiwari13",
    "likes": 1,
    "time": 1738403719,
    "date": "2025-02-01 09:55:19",
    "video_id": "mIHzEZfB334",
    "is_reply": false,
    "extraction_method": "youtube_api",
    "sentiment": "neutral",
    "sentiment_score": 0.5285484790802002,
    "oem": "Ola Electric",
    "month": "2025-01"
  },
  {
    "text": "Ola s1 pro gen2 le ya gen 3 ?",
    "author": "@dibyenduchakraborty3844",
    "likes": 1,
    "time": 1738403542,
    "date": "2025-02-01 09:52:22",
    "video_id": "mIHzEZfB334",
    "is_reply": false,
    "extraction_method": "youtube_api",
    "sentiment": "neutral",
    "sentiment_score": 0.8018808364868164,
    "oem": "Ola Electric",
    "month": "2025-01"
  },
  {
    "text": "Chatek sahi hai",
    "author": "@RahulYadav-ty7lk",
    "likes": 4,
    "time": 1738403090,
    "date": "2025-02-01 09:44:50",
    "video_id": "mIHzEZfB334",
    "is_reply": false,
    "extraction_method": "youtube_api",
    "sentiment": "positive",
    "sentiment_score": 0.3675428032875061,
    "oem": "Ola Electric",
    "month": "2025-01"
  },
  {
    "text": "Bhaiya move os 5 ka update..... aur bhaiya aap ye month to month EV sales report banate ho na... i personally like it.... good knowledge ❤",
    "author": "@randomthings7915",
    "likes": 1,
    "time": 1738403046,
    "date": "2025-02-01 09:44:06",
    "video_id": "mIHzEZfB334",
    "is_reply": false,
    "extraction_method": "youtube_api",
    "sentiment": "positive",
    "sentiment_score": 0.49551108479499817,
    "oem": "Ola Electric",
    "month": "2025-01"
  },
  {
    "text": "Bhaiya bataiye kya lena thik rahega ev scooter mei , budget 1 lakh",
    "author": "@wandereradvit023",
    "likes": 1,
    "time": 1738402628,
    "date": "2025-02-01 09:37:08",
    "video_id": "mIHzEZfB334",
    "is_reply": false,
    "extraction_method": "youtube_api",
    "sentiment": "neutral",
    "sentiment_score": 0.3647019863128662,
    "oem": "Ola Electric",
    "month": "2025-01"
  },
  {
    "text": "still Chetak is better than all",
    "author": "@kartik69969",
    "likes": 3,
    "time": 1738402621,
    "date": "2025-02-01 09:37:01",
    "video_id": "mIHzEZfB334",
    "is_reply": false,
    "extraction_method": "youtube_api",
    "sentiment": "positive",
    "sentiment_score": 0.5314396619796753,
    "oem": "Ola Electric",
    "month": "2025-01"
  },
  {
    "text": "Activa kha gya Kahi dikh nahi Raha 😅😅",
    "author": "@honeytaneja1960",
    "likes": 3,
    "time": 1738402210,
    "date": "2025-02-01 09:30:10",
    "video_id": "mIHzEZfB334",
    "is_reply": false,
    "extraction_method": "youtube_api",
    "sentiment": "neutral",
    "sentiment_score": 0.35621190071105957,
    "oem": "Ola Electric",
    "month": "2025-01"
  },
  {
    "text": "The King Is Back 👑 Ola🎉  Service Very Improved Now",
    "author": "@MLUKMAAN8",
    "likes": 34,
    "time": 1738402042,
    "date": "2025-02-01 09:27:22",
    "video_id": "mIHzEZfB334",
    "is_reply": false,
    "extraction_method": "youtube_api",
    "sentiment": "positive",
    "sentiment_score": 0.8985980749130249,
    "oem": "Ola Electric",
    "month": "2025-01"
  },
  {
    "text": "Hn improve hua hai",
    "author": "@Rabindra-dp3rc2xi7x",
    "likes": 1,
    "time": 1738400931,
    "date": "2025-02-01 09:08:51",
    "video_id": "mIHzEZfB334",
    "is_reply": false,
    "extraction_method": "youtube_api",
    "sentiment": "positive",
    "sentiment_score": 0.4345097541809082,
    "oem": "Ola Electric",
    "month": "2025-01"
  },
  {
    "text": "Ather best hai lekin over price hai service mein aur pro pack mein 😢",
    "author": "@Rabindra-dp3rc2xi7x",
    "likes": 8,
    "time": 1738400534,
    "date": "2025-02-01 09:02:14",
    "video_id": "mIHzEZfB334",
    "is_reply": false,
    "extraction_method": "youtube_api",
    "sentiment": "negative",
    "sentiment_score": 0.6928426623344421,
    "oem": "Ola Electric",
    "month": "2025-01"
  },
  {
    "text": "Bhai ola s1x 4 kwh  reviews",
    "author": "@YashvardhanSingh-bw2bl",
    "likes": 2,
    "time": 1738400494,
    "date": "2025-02-01 09:01:34",
    "video_id": "mIHzEZfB334",
    "is_reply": false,
    "extraction_method": "youtube_api",
    "sentiment": "neutral",
    "sentiment_score": 0.7443704009056091,
    "oem": "Ola Electric",
    "month": "2025-01"
  },
  {
    "text": "Bro second comment Mai Apka bada fan hun heart please 😢",
    "author": "@StroceoGaming",
    "likes": 1,
    "time": 1738400418,
    "date": "2025-02-01 09:00:18",
    "video_id": "mIHzEZfB334",
    "is_reply": false,
    "extraction_method": "youtube_api",
    "sentiment": "positive",
    "sentiment_score": 0.5025428533554077,
    "oem": "Ola Electric",
    "month": "2025-01"
  },
  {
    "text": "Ampere magnus neo😍best budget scooter for city ride with better build quality than ola s1x",
    "author": "@abhishek5931",
    "likes": 4,
    "time": 1738400412,
    "date": "2025-02-01 09:00:12",
    "video_id": "mIHzEZfB334",
    "is_reply": false,
    "extraction_method": "youtube_api",
    "sentiment": "positive",
    "sentiment_score": 0.7883323431015015,
    "oem": "Ola Electric",
    "month": "2025-01"
  },
  {
    "text": "Mp",
    "author": "@saloniyadav7688",
    "likes": 0,
    "time": 1740012394,
    "date": "2025-02-20 00:46:34",
    "video_id": "N6GZh21--Ow",
    "is_reply": false,
    "extraction_method": "youtube_api",
    "sentiment": "neutral",
    "sentiment_score": 0.4384717345237732,
    "oem": "Ola Electric",
    "month": "2025-01"
  },
  {
    "text": "Ola highest sale in Odisha",
    "author": "@sanatkumarbehera6106",
    "likes": 0,
    "time": 1738552105,
    "date": "2025-02-03 03:08:25",
    "video_id": "N6GZh21--Ow",
    "is_reply": false,
    "extraction_method": "youtube_api",
    "sentiment": "neutral",
    "sentiment_score": 0.626775860786438,
    "oem": "Ola Electric",
    "month": "2025-01"
  },
  {
    "text": "U P lucknow",
    "author": "@mevivek8462",
    "likes": 0,
    "time": 1738512529,
    "date": "2025-02-02 16:08:49",
    "video_id": "N6GZh21--Ow",
    "is_reply": false,
    "extraction_method": "youtube_api",
    "sentiment": "neutral",
    "sentiment_score": 0.44318273663520813,
    "oem": "Ola Electric",
    "month": "2025-01"
  },
  {
    "text": "Ola was always leader you make videos on 15😄🔁20 days to gain some likes by Bajaj and tvs people😂",
    "author": "@lovenagpal.6504",
    "likes": 0,
    "time": 1740079661,
    "date": "2025-02-20 19:27:41",
    "video_id": "CKt69dViZvU",
    "is_reply": false,
    "extraction_method": "youtube_api",
    "sentiment": "positive",
    "sentiment_score": 0.4725959300994873,
    "oem": "Ola Electric",
    "month": "2025-01"
  },
  {
    "text": "Electric market ne loot macha rakhi hai , Cheap and best Electric Scooter kab 2026 ke Last me Aayega",
    "author": "@ramakantmauryalucknow6574",
    "likes": 0,
    "time": 1738430937,
    "date": "2025-02-01 17:28:57",
    "video_id": "CKt69dViZvU",
    "is_reply": false,
    "extraction_method": "youtube_api",
    "sentiment": "positive",
    "sentiment_score": 0.3639208674430847,
    "oem": "Ola Electric",
    "month": "2025-01"
  },
  {
    "text": "The King is back 👑 Ola 🎉",
    "author": "@MLUKMAAN8",
    "likes": 2,
    "time": 1738425565,
    "date": "2025-02-01 15:59:25",
    "video_id": "CKt69dViZvU",
    "is_reply": false,
    "extraction_method": "youtube_api",
    "sentiment": "positive",
    "sentiment_score": 0.8650983572006226,
    "oem": "Ola Electric",
    "month": "2025-01"
  },
  {
    "text": "I'm based in Bhubaneswar, Odisha. I'm 57 years old. My daily commute is 65 kms on average. Which one will be a good scooter for 8 years, easy & comfortable ride experience and value for money scooter brand please suggest.",
    "author": "@susantapanda1225",
    "likes": 0,
    "time": 1738408653,
    "date": "2025-02-01 11:17:33",
    "video_id": "CKt69dViZvU",
    "is_reply": false,
    "extraction_method": "youtube_api",
    "sentiment": "positive",
    "sentiment_score": 0.515600860118866,
    "oem": "Ola Electric",
    "month": "2025-01"
  },
  {
    "text": "Electric is future.. numbers will only increase👍",
    "author": "@abhishek5931",
    "likes": 0,
    "time": 1738404552,
    "date": "2025-02-01 10:09:12",
    "video_id": "CKt69dViZvU",
    "is_reply": false,
    "extraction_method": "youtube_api",
    "sentiment": "positive",
    "sentiment_score": 0.7998782396316528,
    "oem": "Ola Electric",
    "month": "2025-01"
  },
  {
    "text": "Ola was best",
    "author": "@satyanayak1489",
    "likes": 1,
    "time": 1738401096,
    "date": "2025-02-01 09:11:36",
    "video_id": "CKt69dViZvU",
    "is_reply": false,
    "extraction_method": "youtube_api",
    "sentiment": "positive",
    "sentiment_score": 0.638031005859375,
    "oem": "Ola Electric",
    "month": "2025-01"
  },
  {
    "text": "Me hu ap fist 👊🏻 view'",
    "author": "@nobitaanddoremon4795",
    "likes": 0,
    "time": 1738400210,
    "date": "2025-02-01 08:56:50",
    "video_id": "CKt69dViZvU",
    "is_reply": false,
    "extraction_method": "youtube_api",
    "sentiment": "positive",
    "sentiment_score": 0.410521924495697,
    "oem": "Ola Electric",
    "month": "2025-01"
  },
  {
    "text": "First view",
    "author": "@nobitaanddoremon4795",
    "likes": 0,
    "time": 1738400188,
    "date": "2025-02-01 08:56:28",
    "video_id": "CKt69dViZvU",
    "is_reply": false,
    "extraction_method": "youtube_api",
    "sentiment": "neutral",
    "sentiment_score": 0.487875759601593,
    "oem": "Ola Electric",
    "month": "2025-01"
  },
  {
    "text": "can confirm: he never gave us up",
    "author": "@YouTube",
    "likes": 89037,
    "time": 1745348708,
    "date": "2025-04-22 19:05:08",
    "video_id": "dQw4w9WgXcQ",
    "is_reply": false,
    "extraction_method": "youtube_api",
    "sentiment": "neutral",
    "sentiment_score": 0.43576160073280334,
    "oem": "Ola Electric",
    "month": "2025-01"
  },
  {
    "text": "I really fell for this huh?",
    "author": "@TheNuclearNutBlaster69",
    "likes": 0,
    "time": 1755421992,
    "date": "2025-08-17 09:13:12",
    "video_id": "dQw4w9WgXcQ",
    "is_reply": false,
    "extraction_method": "youtube_api",
    "sentiment": "negative",
    "sentiment_score": 0.8154076337814331,
    "oem": "Ola Electric",
    "month": "2025-01"
  },
  {
    "text": "Can confirm he rickrolled us a lot using different links",
    "author": "@CarnageCody-e1k",
    "likes": 0,
    "time": 1755421868,
    "date": "2025-08-17 09:11:08",
    "video_id": "dQw4w9WgXcQ",
    "is_reply": false,
    "extraction_method": "youtube_api",
    "sentiment": "negative",
    "sentiment_score": 0.6219365000724792,
    "oem": "Ola Electric",
    "month": "2025-01"
  },
  {
    "text": "But link say free robux",
    "author": "@Therealmegaman",
    "likes": 0,
    "time": 1755421592,
    "date": "2025-08-17 09:06:32",
    "video_id": "dQw4w9WgXcQ",
    "is_reply": false,
    "extraction_method": "youtube_api",
    "sentiment": "neutral",
    "sentiment_score": 0.6602441072463989,
    "oem": "Ola Electric",
    "month": "2025-01"
  },
  {
    "text": "I was here cuz a short said the vid got taken down I thought it was real",
    "author": "@userpotato123",
    "likes": 0,
    "time": 1755421565,
    "date": "2025-08-17 09:06:05",
    "video_id": "dQw4w9WgXcQ",
    "is_reply": false,
    "extraction_method": "youtube_api",
    "sentiment": "negative",
    "sentiment_score": 0.5890551209449768,
    "oem": "Ola Electric",
    "month": "2025-01"
  },
  {
    "text": "Using the link to rickroll my mates",
    "author": "@SerenParfitt",
    "likes": 0,
    "time": 1755420925,
    "date": "2025-08-17 08:55:25",
    "video_id": "dQw4w9WgXcQ",
    "is_reply": false,
    "extraction_method": "youtube_api",
    "sentiment": "neutral",
    "sentiment_score": 0.713318407535553,
    "oem": "Ola Electric",
    "month": "2025-01"
  },
  {
    "text": "i got rick rolled😞",
    "author": "@DheerajVarma-qz2ck",
    "likes": 0,
    "time": 1755420769,
    "date": "2025-08-17 08:52:49",
    "video_id": "dQw4w9WgXcQ",
    "is_reply": false,
    "extraction_method": "youtube_api",
    "sentiment": "negative",
    "sentiment_score": 0.8817840814590454,
    "oem": "Ola Electric",
    "month": "2025-01"
  },
  {
    "text": "1b people: 🗿",
    "author": "@mcdonalds2025-m5f",
    "likes": 1,
    "time": 1755420236,
    "date": "2025-08-17 08:43:56",
    "video_id": "dQw4w9WgXcQ",
    "is_reply": false,
    "extraction_method": "youtube_api",
    "sentiment": "negative",
    "sentiment_score": 0.6539536714553833,
    "oem": "Ola Electric",
    "month": "2025-01"
  },
  {
    "text": "i didint type that :(",
    "author": "@orange_sparklez",
    "likes": 0,
    "time": 1755419984,
    "date": "2025-08-17 08:39:44",
    "video_id": "dQw4w9WgXcQ",
    "is_reply": false,
    "extraction_method": "youtube_api",
    "sentiment": "negative",
    "sentiment_score": 0.8598254323005676,
    "oem": "Ola Electric",
    "month": "2025-01"
  },
  {
    "text": "wait",
    "author": "@orange_sparklez",
    "likes": 0,
    "time": 1755419971,
    "date": "2025-08-17 08:39:31",
    "video_id": "dQw4w9WgXcQ",
    "is_reply": false,
    "extraction_method": "youtube_api",
    "sentiment": "neutral",
    "sentiment_score": 0.45277535915374756,
    "oem": "Ola Electric",
    "month": "2025-01"
  },
  {
    "text": "People from wplace\n👇️",
    "author": "@mendori_true",
    "likes": 3,
    "time": 1755419923,
    "date": "2025-08-17 08:38:43",
    "video_id": "dQw4w9WgXcQ",
    "is_reply": false,
    "extraction_method": "youtube_api",
    "sentiment": "neutral",
    "sentiment_score": 0.749089777469635,
    "oem": "Ola Electric",
    "month": "2025-01"
  },
  {
    "text": "I Rick-Roll Myself on a daily Basis! You can't quit me yet.",
    "author": "@zylo2246",
    "likes": 0,
    "time": 1755418880,
    "date": "2025-08-17 08:21:20",
    "video_id": "dQw4w9WgXcQ",
    "is_reply": false,
    "extraction_method": "youtube_api",
    "sentiment": "neutral",
    "sentiment_score": 0.5509579181671143,
    "oem": "Ola Electric",
    "month": "2025-01"
  },
  {
    "text": "People who came from Spu7nix\n👇",
    "author": "@Visionary2901",
    "likes": 0,
    "time": 1755418619,
    "date": "2025-08-17 08:16:59",
    "video_id": "dQw4w9WgXcQ",
    "is_reply": false,
    "extraction_method": "youtube_api",
    "sentiment": "neutral",
    "sentiment_score": 0.8609896898269653,
    "oem": "Ola Electric",
    "month": "2025-01"
  },
  {
    "text": "I guess this is the most copied link on youtube😂😂😂",
    "author": "@boss_slt8478",
    "likes": 2,
    "time": 1755418274,
    "date": "2025-08-17 08:11:14",
    "video_id": "dQw4w9WgXcQ",
    "is_reply": false,
    "extraction_method": "youtube_api",
    "sentiment": "neutral",
    "sentiment_score": 0.5487360954284668,
    "oem": "Ola Electric",
    "month": "2025-01"
  },
  {
    "text": "Omega-layers mean: get Layer λ now [working 2020]\nMe mean:Click 1 times video on it",
    "author": "@ICYshde",
    "likes": 0,
    "time": 1755417763,
    "date": "2025-08-17 08:02:43",
    "video_id": "dQw4w9WgXcQ",
    "is_reply": false,
    "extraction_method": "youtube_api",
    "sentiment": "neutral",
    "sentiment_score": 0.8226398229598999,
    "oem": "Ola Electric",
    "month": "2025-01"
  },
  {
    "text": "But I thought it was free candy blossom 😢",
    "author": "@ParakeetGaming2",
    "likes": 2,
    "time": 1755414788,
    "date": "2025-08-17 07:13:08",
    "video_id": "dQw4w9WgXcQ",
    "is_reply": false,
    "extraction_method": "youtube_api",
    "sentiment": "negative",
    "sentiment_score": 0.8306077122688293,
    "oem": "Ola Electric",
    "month": "2025-01"
  },
  {
    "text": "It said free robux",
    "author": "@theroyalmunicdude",
    "likes": 0,
    "time": 1755414753,
    "date": "2025-08-17 07:12:33",
    "video_id": "dQw4w9WgXcQ",
    "is_reply": false,
    "extraction_method": "youtube_api",
    "sentiment": "neutral",
    "sentiment_score": 0.7164434790611267,
    "oem": "Ola Electric",
    "month": "2025-01"
  },
  {
    "text": "комментарии излишни...моя юность",
    "author": "@МирЫч-э4в",
    "likes": 0,
    "time": 1755413588,
    "date": "2025-08-17 06:53:08",
    "video_id": "dQw4w9WgXcQ",
    "is_reply": false,
    "extraction_method": "youtube_api",
    "sentiment": "negative",
    "sentiment_score": 0.8300111293792725,
    "oem": "Ola Electric",
    "month": "2025-01"
  },
  {
    "text": "To that guy who posted a IG reel where it said that the video got deleted.\n\nYou got me",
    "author": "@anticucho-qliaouwu5070",
    "likes": 5,
    "time": 1755413357,
    "date": "2025-08-17 06:49:17",
    "video_id": "dQw4w9WgXcQ",
    "is_reply": false,
    "extraction_method": "youtube_api",
    "sentiment": "negative",
    "sentiment_score": 0.5776676535606384,
    "oem": "Ola Electric",
    "month": "2025-01"
  },
  {
    "text": "never should've scanned that qr code",
    "author": "@Expungedcontent",
    "likes": 4,
    "time": 1755413034,
    "date": "2025-08-17 06:43:54",
    "video_id": "dQw4w9WgXcQ",
    "is_reply": false,
    "extraction_method": "youtube_api",
    "sentiment": "negative",
    "sentiment_score": 0.6970016956329346,
    "oem": "Ola Electric",
    "month": "2025-01"
  },
  {
    "text": "Mengapa orang ini dibenci?",
    "author": "@nanda-oficial797",
    "likes": 2,
    "time": 1755412592,
    "date": "2025-08-17 06:36:32",
    "video_id": "dQw4w9WgXcQ",
    "is_reply": false,
    "extraction_method": "youtube_api",
    "sentiment": "negative",
    "sentiment_score": 0.908707320690155,
    "oem": "Ola Electric",
    "month": "2025-01"
  },
  {
    "text": "Such a banger, all these years later",
    "author": "@Klespyrian",
    "likes": 0,
    "time": 1755412208,
    "date": "2025-08-17 06:30:08",
    "video_id": "dQw4w9WgXcQ",
    "is_reply": false,
    "extraction_method": "youtube_api",
    "sentiment": "positive",
    "sentiment_score": 0.8817105889320374,
    "oem": "Ola Electric",
    "month": "2025-01"
  },
  {
    "text": "Im so suprised this was a pupolar song and also a meme and prank os crazy and this has 1billion views",
    "author": "@angelinabaquir4903",
    "likes": 0,
    "time": 1755412012,
    "date": "2025-08-17 06:26:52",
    "video_id": "dQw4w9WgXcQ",
    "is_reply": false,
    "extraction_method": "youtube_api",
    "sentiment": "negative",
    "sentiment_score": 0.4594791531562805,
    "oem": "Ola Electric",
    "month": "2025-01"
  },
  {
    "text": "DAMN YOU WPLACE!!!!",
    "author": "@eShopbag",
    "likes": 2,
    "time": 1755410701,
    "date": "2025-08-17 06:05:01",
    "video_id": "dQw4w9WgXcQ",
    "is_reply": false,
    "extraction_method": "youtube_api",
    "sentiment": "negative",
    "sentiment_score": 0.7656681537628174,
    "oem": "Ola Electric",
    "month": "2025-01"
  },
  {
    "text": "Damn you rey",
    "author": "@dayli-el5kf",
    "likes": 0,
    "time": 1755410394,
    "date": "2025-08-17 05:59:54",
    "video_id": "dQw4w9WgXcQ",
    "is_reply": false,
    "extraction_method": "youtube_api",
    "sentiment": "negative",
    "sentiment_score": 0.5147788524627686,
    "oem": "Ola Electric",
    "month": "2025-01"
  },
  {
    "text": "GET RICKROLLED (prank for everyone)",
    "author": "@Ethanaperez19",
    "likes": 0,
    "time": 1755410340,
    "date": "2025-08-17 05:59:00",
    "video_id": "dQw4w9WgXcQ",
    "is_reply": false,
    "extraction_method": "youtube_api",
    "sentiment": "negative",
    "sentiment_score": 0.7568674683570862,
    "oem": "Ola Electric",
    "month": "2025-01"
  },
  {
    "text": "um",
    "author": "@madaisidoro9489",
    "likes": 0,
    "time": 1755410162,
    "date": "2025-08-17 05:56:02",
    "video_id": "dQw4w9WgXcQ",
    "is_reply": false,
    "extraction_method": "youtube_api",
    "sentiment": "neutral",
    "sentiment_score": 0.41008204221725464,
    "oem": "Ola Electric",
    "month": "2025-01"
  },
  {
    "text": "This is not free robux 😢😢😢",
    "author": "@IuisgamercoI23",
    "likes": 0,
    "time": 1755409848,
    "date": "2025-08-17 05:50:48",
    "video_id": "dQw4w9WgXcQ",
    "is_reply": false,
    "extraction_method": "youtube_api",
    "sentiment": "negative",
    "sentiment_score": 0.881257951259613,
    "oem": "Ola Electric",
    "month": "2025-01"
  },
  {
    "text": "I was told that there are free robux here (this is a joke, they didn't rick me)",
    "author": "@rustamaxmedxanov3099",
    "likes": 0,
    "time": 1755409840,
    "date": "2025-08-17 05:50:40",
    "video_id": "dQw4w9WgXcQ",
    "is_reply": false,
    "extraction_method": "youtube_api",
    "sentiment": "neutral",
    "sentiment_score": 0.4195407032966614,
    "oem": "Ola Electric",
    "month": "2025-01"
  },
  {
    "text": "Would anyone tell me what's next to get my free robux?",
    "author": "@KevinMitnickHKR",
    "likes": 0,
    "time": 1755409803,
    "date": "2025-08-17 05:50:03",
    "video_id": "dQw4w9WgXcQ",
    "is_reply": false,
    "extraction_method": "youtube_api",
    "sentiment": "neutral",
    "sentiment_score": 0.8051230907440186,
    "oem": "Ola Electric",
    "month": "2025-01"
  },
  {
    "text": "Wait this isn't free robux😭😭",
    "author": "@S_chaos",
    "likes": 2,
    "time": 1755409048,
    "date": "2025-08-17 05:37:28",
    "video_id": "dQw4w9WgXcQ",
    "is_reply": false,
    "extraction_method": "youtube_api",
    "sentiment": "negative",
    "sentiment_score": 0.6235840320587158,
    "oem": "Ola Electric",
    "month": "2025-01"
  },
  {
    "text": "I got Rick Rolled by wplace... Thanks France for that",
    "author": "@White_Slaughter",
    "likes": 2,
    "time": 1755408973,
    "date": "2025-08-17 05:36:13",
    "video_id": "dQw4w9WgXcQ",
    "is_reply": false,
    "extraction_method": "youtube_api",
    "sentiment": "positive",
    "sentiment_score": 0.6662169694900513,
    "oem": "Ola Electric",
    "month": "2025-01"
  },
  {
    "text": "Mmh well, description don't tell that INTERNET made it a classic, before that no one ever heard about this song, so... thanks internet in the description maybe ? Instead of lying about those so-called Top US billboards ? Psssst billboards come after 4chan made your legend, please, be grateful Rick.",
    "author": "@flajelata",
    "likes": 1,
    "time": 1755408909,
    "date": "2025-08-17 05:35:09",
    "video_id": "dQw4w9WgXcQ",
    "is_reply": false,
    "extraction_method": "youtube_api",
    "sentiment": "negative",
    "sentiment_score": 0.4707251787185669,
    "oem": "Ola Electric",
    "month": "2025-01"
  },
  {
    "text": "Trust me, I came here on my own.",
    "author": "@조성호-e6r",
    "likes": 2,
    "time": 1755408573,
    "date": "2025-08-17 05:29:33",
    "video_id": "dQw4w9WgXcQ",
    "is_reply": false,
    "extraction_method": "youtube_api",
    "sentiment": "neutral",
    "sentiment_score": 0.4777374863624573,
    "oem": "Ola Electric",
    "month": "2025-01"
  },
  {
    "text": "I tattooed the QR code for this video on my arm, and now everyone scans it. It was totally worth it",
    "author": "@froy_snz",
    "likes": 2,
    "time": 1755408201,
    "date": "2025-08-17 05:23:21",
    "video_id": "dQw4w9WgXcQ",
    "is_reply": false,
    "extraction_method": "youtube_api",
    "sentiment": "positive",
    "sentiment_score": 0.7756262421607971,
    "oem": "Ola Electric",
    "month": "2025-01"
  },
  {
    "text": "Got Rickrolled",
    "author": "@DeMak3512",
    "likes": 1,
    "time": 1755407599,
    "date": "2025-08-17 05:13:19",
    "video_id": "dQw4w9WgXcQ",
    "is_reply": false,
    "extraction_method": "youtube_api",
    "sentiment": "neutral",
    "sentiment_score": 0.481034517288208,
    "oem": "Ola Electric",
    "month": "2025-01"
  },
  {
    "text": "15 YEARS BABYY",
    "author": "@çalışmamasası-t9s",
    "likes": 1,
    "time": 1755407433,
    "date": "2025-08-17 05:10:33",
    "video_id": "dQw4w9WgXcQ",
    "is_reply": false,
    "extraction_method": "youtube_api",
    "sentiment": "positive",
    "sentiment_score": 0.5289790034294128,
    "oem": "Ola Electric",
    "month": "2025-01"
  },
  {
    "text": "Quien más vino por un QR hecho en Wplace XD",
    "author": "@Alexzkai00",
    "likes": 2,
    "time": 1755407270,
    "date": "2025-08-17 05:07:50",
    "video_id": "dQw4w9WgXcQ",
    "is_reply": false,
    "extraction_method": "youtube_api",
    "sentiment": "neutral",
    "sentiment_score": 0.7341232895851135,
    "oem": "Ola Electric",
    "month": "2025-01"
  },
  {
    "text": "Dam you chinese people!!! (Wplace)",
    "author": "@Kratos....",
    "likes": 0,
    "time": 1755407046,
    "date": "2025-08-17 05:04:06",
    "video_id": "dQw4w9WgXcQ",
    "is_reply": false,
    "extraction_method": "youtube_api",
    "sentiment": "negative",
    "sentiment_score": 0.8446906208992004,
    "oem": "Ola Electric",
    "month": "2025-01"
  },
  {
    "text": "I was born this song was made😂😂😂",
    "author": "@Key_on-x1v",
    "likes": 1,
    "time": 1755405577,
    "date": "2025-08-17 04:39:37",
    "video_id": "dQw4w9WgXcQ",
    "is_reply": false,
    "extraction_method": "youtube_api",
    "sentiment": "neutral",
    "sentiment_score": 0.5516175031661987,
    "oem": "Ola Electric",
    "month": "2025-01"
  },
  {
    "text": "Huh wheres my robux",
    "author": "@basketball_omega",
    "likes": 1,
    "time": 1755405083,
    "date": "2025-08-17 04:31:23",
    "video_id": "dQw4w9WgXcQ",
    "is_reply": false,
    "extraction_method": "youtube_api",
    "sentiment": "negative",
    "sentiment_score": 0.7465588450431824,
    "oem": "Ola Electric",
    "month": "2025-01"
  },
  {
    "text": "W place damm you",
    "author": "@Johnnotbutstuff",
    "likes": 1,
    "time": 1755404251,
    "date": "2025-08-17 04:17:31",
    "video_id": "dQw4w9WgXcQ",
    "is_reply": false,
    "extraction_method": "youtube_api",
    "sentiment": "negative",
    "sentiment_score": 0.4036899507045746,
    "oem": "Ola Electric",
    "month": "2025-01"
  },
  {
    "text": "One day, we'll miss being rickrolled",
    "author": "@Nexyzero97",
    "likes": 0,
    "time": 1755404232,
    "date": "2025-08-17 04:17:12",
    "video_id": "dQw4w9WgXcQ",
    "is_reply": false,
    "extraction_method": "youtube_api",
    "sentiment": "negative",
    "sentiment_score": 0.8868758082389832,
    "oem": "Ola Electric",
    "month": "2025-01"
  },
  {
    "text": "But the link said free robux",
    "author": "@Dreamgaming5052",
    "likes": 0,
    "time": 1755404138,
    "date": "2025-08-17 04:15:38",
    "video_id": "dQw4w9WgXcQ",
    "is_reply": false,
    "extraction_method": "youtube_api",
    "sentiment": "neutral",
    "sentiment_score": 0.7138314247131348,
    "oem": "Ola Electric",
    "month": "2025-01"
  },
  {
    "text": "LIKE LOS QUE VENGAN DEL QR DEL GOLFO DE MEXICO",
    "author": "@kimdramas6302",
    "likes": 0,
    "time": 1755404008,
    "date": "2025-08-17 04:13:28",
    "video_id": "dQw4w9WgXcQ",
    "is_reply": false,
    "extraction_method": "youtube_api",
    "sentiment": "neutral",
    "sentiment_score": 0.5558990836143494,
    "oem": "Ola Electric",
    "month": "2025-01"
  },
  {
    "text": "QR DE WPLACE😂",
    "author": "@DanielChileno",
    "likes": 0,
    "time": 1755403999,
    "date": "2025-08-17 04:13:19",
    "video_id": "dQw4w9WgXcQ",
    "is_reply": false,
    "extraction_method": "youtube_api",
    "sentiment": "neutral",
    "sentiment_score": 0.8016911745071411,
    "oem": "Ola Electric",
    "month": "2025-01"
  },
  {
    "text": "Found this from a QR code in a tf2  2 fort server",
    "author": "@Mimikyu_Posting",
    "likes": 0,
    "time": 1755403906,
    "date": "2025-08-17 04:11:46",
    "video_id": "dQw4w9WgXcQ",
    "is_reply": false,
    "extraction_method": "youtube_api",
    "sentiment": "neutral",
    "sentiment_score": 0.8111560344696045,
    "oem": "Ola Electric",
    "month": "2025-01"
  },
  {
    "text": "My friend blue lobster send me this when me and dave the octopus talking about goldfish(my gf).",
    "author": "@KillerfishAndTasteReallyGood",
    "likes": 0,
    "time": 1755403765,
    "date": "2025-08-17 04:09:25",
    "video_id": "dQw4w9WgXcQ",
    "is_reply": false,
    "extraction_method": "youtube_api",
    "sentiment": "neutral",
    "sentiment_score": 0.5316843390464783,
    "oem": "Ola Electric",
    "month": "2025-01"
  },
  {
    "text": "BRUH ANYONE ELSE HERE FROM THE SMOSH QR CODE??\nL",
    "author": "@I-eat-dirt456",
    "likes": 0,
    "time": 1755402375,
    "date": "2025-08-17 03:46:15",
    "video_id": "dQw4w9WgXcQ",
    "is_reply": false,
    "extraction_method": "youtube_api",
    "sentiment": "negative",
    "sentiment_score": 0.5575353503227234,
    "oem": "Ola Electric",
    "month": "2025-01"
  },
  {
    "text": "Rick rolling since 1987.",
    "author": "@yennydavila5056",
    "likes": 2,
    "time": 1755402308,
    "date": "2025-08-17 03:45:08",
    "video_id": "dQw4w9WgXcQ",
    "is_reply": false,
    "extraction_method": "youtube_api",
    "sentiment": "neutral",
    "sentiment_score": 0.626618504524231,
    "oem": "Ola Electric",
    "month": "2025-01"
  },
  {
    "text": "❤❤",
    "author": "@DucHoang-j9w6c",
    "likes": 0,
    "time": 1755402017,
    "date": "2025-08-17 03:40:17",
    "video_id": "dQw4w9WgXcQ",
    "is_reply": false,
    "extraction_method": "youtube_api",
    "sentiment": "positive",
    "sentiment_score": 0.6299543380737305,
    "oem": "Ola Electric",
    "month": "2025-01"
  },
  {
    "text": "DAMM IT, I felt on another QR code prank 😅",
    "author": "@lokitunes4256",
    "likes": 2,
    "time": 1755401676,
    "date": "2025-08-17 03:34:36",
    "video_id": "dQw4w9WgXcQ",
    "is_reply": false,
    "extraction_method": "youtube_api",
    "sentiment": "negative",
    "sentiment_score": 0.5214509963989258,
    "oem": "Ola Electric",
    "month": "2025-01"
  },
  {
    "text": "I was Rick rolled. It said he would give me free Robux.!!!",
    "author": "@EllaHershman-i8e",
    "likes": 0,
    "time": 1755401595,
    "date": "2025-08-17 03:33:15",
    "video_id": "dQw4w9WgXcQ",
    "is_reply": false,
    "extraction_method": "youtube_api",
    "sentiment": "neutral",
    "sentiment_score": 0.6024361848831177,
    "oem": "Ola Electric",
    "month": "2025-01"
  },
  {
    "text": "anybody else from that one instagram reel where it said it was removed😭🤦🏾‍♂️🤦🏾‍♂️🤦🏾‍♂️",
    "author": "@sunabi_94",
    "likes": 2,
    "time": 1755401486,
    "date": "2025-08-17 03:31:26",
    "video_id": "dQw4w9WgXcQ",
    "is_reply": false,
    "extraction_method": "youtube_api",
    "sentiment": "negative",
    "sentiment_score": 0.7767454981803894,
    "oem": "Ola Electric",
    "month": "2025-01"
  },
  {
    "text": "The gulf of Mexico in wplace is what led me here.",
    "author": "@Indieman_Fan",
    "likes": 0,
    "time": 1755401433,
    "date": "2025-08-17 03:30:33",
    "video_id": "dQw4w9WgXcQ",
    "is_reply": false,
    "extraction_method": "youtube_api",
    "sentiment": "neutral",
    "sentiment_score": 0.4431113004684448,
    "oem": "Ola Electric",
    "month": "2025-01"
  },
  {
    "text": "Rickroll",
    "author": "@sulochanabhate5177",
    "likes": 0,
    "time": 1755401231,
    "date": "2025-08-17 03:27:11",
    "video_id": "dQw4w9WgXcQ",
    "is_reply": false,
    "extraction_method": "youtube_api",
    "sentiment": "neutral",
    "sentiment_score": 0.6123101115226746,
    "oem": "Ola Electric",
    "month": "2025-01"
  },
  {
    "text": "Jujutsu kaisen é melhor",
    "author": "@junim0735",
    "likes": 0,
    "time": 1755400658,
    "date": "2025-08-17 03:17:38",
    "video_id": "dQw4w9WgXcQ",
    "is_reply": false,
    "extraction_method": "youtube_api",
    "sentiment": "positive",
    "sentiment_score": 0.46081438660621643,
    "oem": "Ola Electric",
    "month": "2025-01"
  },
  {
    "text": "Bro… this is … GOATED",
    "author": "@bowenwhite3502",
    "likes": 0,
    "time": 1755399887,
    "date": "2025-08-17 03:04:47",
    "video_id": "dQw4w9WgXcQ",
    "is_reply": false,
    "extraction_method": "youtube_api",
    "sentiment": "negative",
    "sentiment_score": 0.4710148572921753,
    "oem": "Ola Electric",
    "month": "2025-01"
  },
  {
    "text": "I wnat the falg !!!",
    "author": "@MmMm-kn3cl",
    "likes": 0,
    "time": 1755399484,
    "date": "2025-08-17 02:58:04",
    "video_id": "dQw4w9WgXcQ",
    "is_reply": false,
    "extraction_method": "youtube_api",
    "sentiment": "negative",
    "sentiment_score": 0.734126091003418,
    "oem": "Ola Electric",
    "month": "2025-01"
  },
  {
    "text": "釣られたクマ〜",
    "author": "@MOONIEMAN",
    "likes": 0,
    "time": 1755399377,
    "date": "2025-08-17 02:56:17",
    "video_id": "dQw4w9WgXcQ",
    "is_reply": false,
    "extraction_method": "youtube_api",
    "sentiment": "negative",
    "sentiment_score": 0.8104333877563477,
    "oem": "Ola Electric",
    "month": "2025-01"
  },
  {
    "text": "Ajg yang ngasih qr di wplace",
    "author": "@Mikarya",
    "likes": 0,
    "time": 1755399310,
    "date": "2025-08-17 02:55:10",
    "video_id": "dQw4w9WgXcQ",
    "is_reply": false,
    "extraction_method": "youtube_api",
    "sentiment": "neutral",
    "sentiment_score": 0.589227020740509,
    "oem": "Ola Electric",
    "month": "2025-01"
  },
  {
    "text": "keren bang lagunya",
    "author": "@thedude-jn6gi",
    "likes": 0,
    "time": 1755398908,
    "date": "2025-08-17 02:48:28",
    "video_id": "dQw4w9WgXcQ",
    "is_reply": false,
    "extraction_method": "youtube_api",
    "sentiment": "positive",
    "sentiment_score": 0.880881130695343,
    "oem": "Ola Electric",
    "month": "2025-01"
  },
  {
    "text": "Bru I got Rick rolled",
    "author": "@BatCat184",
    "likes": 0,
    "time": 1755397754,
    "date": "2025-08-17 02:29:14",
    "video_id": "dQw4w9WgXcQ",
    "is_reply": false,
    "extraction_method": "youtube_api",
    "sentiment": "neutral",
    "sentiment_score": 0.467481404542923,
    "oem": "Ola Electric",
    "month": "2025-01"
  },
  {
    "text": "This isn’t the krabby patty secret formuler",
    "author": "@DCONightingale",
    "likes": 0,
    "time": 1755397396,
    "date": "2025-08-17 02:23:16",
    "video_id": "dQw4w9WgXcQ",
    "is_reply": false,
    "extraction_method": "youtube_api",
    "sentiment": "negative",
    "sentiment_score": 0.4938284754753113,
    "oem": "Ola Electric",
    "month": "2025-01"
  },
  {
    "text": "THE HELL",
    "author": "@Jed-u3n",
    "likes": 0,
    "time": 1755397097,
    "date": "2025-08-17 02:18:17",
    "video_id": "dQw4w9WgXcQ",
    "is_reply": false,
    "extraction_method": "youtube_api",
    "sentiment": "negative",
    "sentiment_score": 0.7978183627128601,
    "oem": "Ola Electric",
    "month": "2025-01"
  },
  {
    "text": "I rickrolled 😢",
    "author": "@eden-y2u",
    "likes": 1,
    "time": 1755396824,
    "date": "2025-08-17 02:13:44",
    "video_id": "dQw4w9WgXcQ",
    "is_reply": false,
    "extraction_method": "youtube_api",
    "sentiment": "negative",
    "sentiment_score": 0.8938503861427307,
    "oem": "Ola Electric",
    "month": "2025-01"
  },
  {
    "text": "rickroll is eternal",
    "author": "@JoaquinAccorroni",
    "likes": 0,
    "time": 1755395184,
    "date": "2025-08-17 01:46:24",
    "video_id": "dQw4w9WgXcQ",
    "is_reply": false,
    "extraction_method": "youtube_api",
    "sentiment": "neutral",
    "sentiment_score": 0.4032370150089264,
    "oem": "Ola Electric",
    "month": "2025-01"
  },
  {
    "text": "汪苏泷😂",
    "author": "@冯Shawn",
    "likes": 0,
    "time": 1755394688,
    "date": "2025-08-17 01:38:08",
    "video_id": "dQw4w9WgXcQ",
    "is_reply": false,
    "extraction_method": "youtube_api",
    "sentiment": "neutral",
    "sentiment_score": 0.58700031042099,
    "oem": "Ola Electric",
    "month": "2025-01"
  },
  {
    "text": "YOU LIAR HOW COULD YOU DO THIS",
    "author": "@Jaxde48",
    "likes": 0,
    "time": 1755393949,
    "date": "2025-08-17 01:25:49",
    "video_id": "dQw4w9WgXcQ",
    "is_reply": false,
    "extraction_method": "youtube_api",
    "sentiment": "negative",
    "sentiment_score": 0.9395608901977539,
    "oem": "Ola Electric",
    "month": "2025-01"
  },
  {
    "text": "Where’s the big bootie latinas :(",
    "author": "@Hesheol",
    "likes": 1,
    "time": 1755393889,
    "date": "2025-08-17 01:24:49",
    "video_id": "dQw4w9WgXcQ",
    "is_reply": false,
    "extraction_method": "youtube_api",
    "sentiment": "negative",
    "sentiment_score": 0.9200329184532166,
    "oem": "Ola Electric",
    "month": "2025-01"
  },
  {
    "text": "Wait ts isnt tge link to gaining every achievement/trophy for every single game,",
    "author": "@BuleKnightgaming",
    "likes": 0,
    "time": 1755393648,
    "date": "2025-08-17 01:20:48",
    "video_id": "dQw4w9WgXcQ",
    "is_reply": false,
    "extraction_method": "youtube_api",
    "sentiment": "neutral",
    "sentiment_score": 0.6497610807418823,
    "oem": "Ola Electric",
    "month": "2025-01"
  },
  {
    "text": "https://youtu.be/RrESvSRNpeo?si=QBNk5lRwhPXcjKGi",
    "author": "@Nayiykit",
    "likes": 0,
    "time": 1755393601,
    "date": "2025-08-17 01:20:01",
    "video_id": "dQw4w9WgXcQ",
    "is_reply": false,
    "extraction_method": "youtube_api",
    "sentiment": "neutral",
    "sentiment_score": 0.6854700446128845,
    "oem": "Ola Electric",
    "month": "2025-01"
  },
  {
    "text": "I fucking fell for it.",
    "author": "@DSCH-Mixer004x",
    "likes": 0,
    "time": 1755393591,
    "date": "2025-08-17 01:19:51",
    "video_id": "dQw4w9WgXcQ",
    "is_reply": false,
    "extraction_method": "youtube_api",
    "sentiment": "negative",
    "sentiment_score": 0.49267178773880005,
    "oem": "Ola Electric",
    "month": "2025-01"
  },
  {
    "text": "1.6 billion",
    "author": "@parkerWatlington-ffo",
    "likes": 0,
    "time": 1755393497,
    "date": "2025-08-17 01:18:17",
    "video_id": "dQw4w9WgXcQ",
    "is_reply": false,
    "extraction_method": "youtube_api",
    "sentiment": "neutral",
    "sentiment_score": 0.48102104663848877,
    "oem": "Ola Electric",
    "month": "2025-01"
  },
  {
    "text": "Getting Rick rolled in the big 25 is crazy",
    "author": "@Himothy512-e8n",
    "likes": 0,
    "time": 1755393492,
    "date": "2025-08-17 01:18:12",
    "video_id": "dQw4w9WgXcQ",
    "is_reply": false,
    "extraction_method": "youtube_api",
    "sentiment": "negative",
    "sentiment_score": 0.778488278388977,
    "oem": "Ola Electric",
    "month": "2025-01"
  },
  {
    "text": "What no free robox",
    "author": "@Mang09huh",
    "likes": 0,
    "time": 1755393246,
    "date": "2025-08-17 01:14:06",
    "video_id": "dQw4w9WgXcQ",
    "is_reply": false,
    "extraction_method": "youtube_api",
    "sentiment": "negative",
    "sentiment_score": 0.7221010327339172,
    "oem": "Ola Electric",
    "month": "2025-01"
  },
  {
    "text": "Here on purpose",
    "author": "@akimbobongs461",
    "likes": 1,
    "time": 1755393100,
    "date": "2025-08-17 01:11:40",
    "video_id": "dQw4w9WgXcQ",
    "is_reply": false,
    "extraction_method": "youtube_api",
    "sentiment": "neutral",
    "sentiment_score": 0.5059983134269714,
    "oem": "Ola Electric",
    "month": "2025-01"
  },
  {
    "text": "沖ノ鳥島から来ました",
    "author": "@battlefaceKYODA98",
    "likes": 7,
    "time": 1755393082,
    "date": "2025-08-17 01:11:22",
    "video_id": "dQw4w9WgXcQ",
    "is_reply": false,
    "extraction_method": "youtube_api",
    "sentiment": "neutral",
    "sentiment_score": 0.6730719208717346,
    "oem": "Ola Electric",
    "month": "2025-01"
  },
  {
    "text": "This isn’t the link to 56 robux?",
    "author": "@YvGh-r3p",
    "likes": 2,
    "time": 1755391710,
    "date": "2025-08-17 00:48:30",
    "video_id": "dQw4w9WgXcQ",
    "is_reply": false,
    "extraction_method": "youtube_api",
    "sentiment": "neutral",
    "sentiment_score": 0.6257769465446472,
    "oem": "Ola Electric",
    "month": "2025-01"
  },
  {
    "text": "15 years later and stil a banger",
    "author": "@orange_pyeel",
    "likes": 23,
    "time": 1755391560,
    "date": "2025-08-17 00:46:00",
    "video_id": "dQw4w9WgXcQ",
    "is_reply": false,
    "extraction_method": "youtube_api",
    "sentiment": "positive",
    "sentiment_score": 0.7912589907646179,
    "oem": "Ola Electric",
    "month": "2025-01"
  },
  {
    "text": "I thought I would get robux",
    "author": "@Sizzler-n6v",
    "likes": 1,
    "time": 1755390905,
    "date": "2025-08-17 00:35:05",
    "video_id": "dQw4w9WgXcQ",
    "is_reply": false,
    "extraction_method": "youtube_api",
    "sentiment": "neutral",
    "sentiment_score": 0.6181921362876892,
    "oem": "Ola Electric",
    "month": "2025-01"
  },
  {
    "text": "I fell for it",
    "author": "@NAnonokey775",
    "likes": 1,
    "time": 1755390550,
    "date": "2025-08-17 00:29:10",
    "video_id": "dQw4w9WgXcQ",
    "is_reply": false,
    "extraction_method": "youtube_api",
    "sentiment": "neutral",
    "sentiment_score": 0.41498497128486633,
    "oem": "Ola Electric",
    "month": "2025-01"
  },
  {
    "text": "I THOUGHT THEY TOOK IT DOWN-CURSED THAT WRETCHED INSTAGRAM REEL",
    "author": "@SamuraiSCTL",
    "likes": 3,
    "time": 1755390449,
    "date": "2025-08-17 00:27:29",
    "video_id": "dQw4w9WgXcQ",
    "is_reply": false,
    "extraction_method": "youtube_api",
    "sentiment": "negative",
    "sentiment_score": 0.9154655933380127,
    "oem": "Ola Electric",
    "month": "2025-01"
  },
  {
    "text": "Bro rickrolled 1.6b people 🙏",
    "author": "@Average_Noobeii",
    "likes": 0,
    "time": 1755390357,
    "date": "2025-08-17 00:25:57",
    "video_id": "dQw4w9WgXcQ",
    "is_reply": false,
    "extraction_method": "youtube_api",
    "sentiment": "positive",
    "sentiment_score": 0.4680354595184326,
    "oem": "Ola Electric",
    "month": "2025-01"
  },
  {
    "text": "but link sayd free robux",
    "author": "@Nobrain-6",
    "likes": 0,
    "time": 1755390105,
    "date": "2025-08-17 00:21:45",
    "video_id": "dQw4w9WgXcQ",
    "is_reply": false,
    "extraction_method": "youtube_api",
    "sentiment": "neutral",
    "sentiment_score": 0.6733399033546448,
    "oem": "Ola Electric",
    "month": "2025-01"
  },
  {
    "text": "AWESOEME",
    "author": "@Beachygirly-b3f",
    "likes": 0,
    "time": 1755390024,
    "date": "2025-08-17 00:20:24",
    "video_id": "dQw4w9WgXcQ",
    "is_reply": false,
    "extraction_method": "youtube_api",
    "sentiment": "negative",
    "sentiment_score": 0.43651729822158813,
    "oem": "Ola Electric",
    "month": "2025-01"
  },
  {
    "text": "Bro, this was in literally a Minecraft server. It was just a QR code on the literal map how",
    "author": "@Aidan-p2w",
    "likes": 0,
    "time": 1755389816,
    "date": "2025-08-17 00:16:56",
    "video_id": "dQw4w9WgXcQ",
    "is_reply": false,
    "extraction_method": "youtube_api",
    "sentiment": "neutral",
    "sentiment_score": 0.675853967666626,
    "oem": "Ola Electric",
    "month": "2025-01"
  },
  {
    "text": "This isn’t 60% off Fandango",
    "author": "@TheLifeKid12",
    "likes": 0,
    "time": 1755389667,
    "date": "2025-08-17 00:14:27",
    "video_id": "dQw4w9WgXcQ",
    "is_reply": false,
    "extraction_method": "youtube_api",
    "sentiment": "negative",
    "sentiment_score": 0.6978940963745117,
    "oem": "Ola Electric",
    "month": "2025-01"
  },
  {
    "text": "❤❤❤",
    "author": "@mariaangelicacabreraencina3586",
    "likes": 2,
    "time": 1755389480,
    "date": "2025-08-17 00:11:20",
    "video_id": "dQw4w9WgXcQ",
    "is_reply": false,
    "extraction_method": "youtube_api",
    "sentiment": "positive",
    "sentiment_score": 0.6913256645202637,
    "oem": "Ola Electric",
    "month": "2025-01"
  },
  {
    "text": "2.4 million people got rickrolled and commented.",
    "author": "@Michi_GD",
    "likes": 2,
    "time": 1755389478,
    "date": "2025-08-17 00:11:18",
    "video_id": "dQw4w9WgXcQ",
    "is_reply": false,
    "extraction_method": "youtube_api",
    "sentiment": "negative",
    "sentiment_score": 0.7604681253433228,
    "oem": "Ola Electric",
    "month": "2025-01"
  },
  {
    "text": "Never gonna give up on music",
    "author": "@starlocal",
    "likes": 2,
    "time": 1755389104,
    "date": "2025-08-17 00:05:04",
    "video_id": "dQw4w9WgXcQ",
    "is_reply": false,
    "extraction_method": "youtube_api",
    "sentiment": "positive",
    "sentiment_score": 0.5783101916313171,
    "oem": "Ola Electric",
    "month": "2025-01"
  },
  {
    "text": "Time to rick roll",
    "author": "@Than_Plays_1",
    "likes": 3,
    "time": 1755388249,
    "date": "2025-08-16 23:50:49",
    "video_id": "dQw4w9WgXcQ",
    "is_reply": false,
    "extraction_method": "youtube_api",
    "sentiment": "neutral",
    "sentiment_score": 0.48441606760025024,
    "oem": "Ola Electric",
    "month": "2025-01"
  },
  {
    "text": "My friend after see it:\nHe: wtf is not fun",
    "author": "@lientran8608",
    "likes": 2,
    "time": 1755387623,
    "date": "2025-08-16 23:40:23",
    "video_id": "dQw4w9WgXcQ",
    "is_reply": false,
    "extraction_method": "youtube_api",
    "sentiment": "negative",
    "sentiment_score": 0.8696776628494263,
    "oem": "Ola Electric",
    "month": "2025-01"
  },
  {
    "text": "wait this isn’t the “learn more” link",
    "author": "@ppretzele",
    "likes": 3,
    "time": 1755386984,
    "date": "2025-08-16 23:29:44",
    "video_id": "dQw4w9WgXcQ",
    "is_reply": false,
    "extraction_method": "youtube_api",
    "sentiment": "neutral",
    "sentiment_score": 0.6265833973884583,
    "oem": "Ola Electric",
    "month": "2025-01"
  },
  {
    "text": "You rickrolled me . I GENUINELY FELL FOR THAT I meant to comment on a another vid but m",
    "author": "@Iceguyanimates",
    "likes": 1,
    "time": 1755386462,
    "date": "2025-08-16 23:21:02",
    "video_id": "dQw4w9WgXcQ",
    "is_reply": false,
    "extraction_method": "youtube_api",
    "sentiment": "negative",
    "sentiment_score": 0.8417848348617554,
    "oem": "Ola Electric",
    "month": "2025-01"
  },
  {
    "text": "I got RickRolled today..... 🥲",
    "author": "@johnibarra9734",
    "likes": 1,
    "time": 1755386093,
    "date": "2025-08-16 23:14:53",
    "video_id": "dQw4w9WgXcQ",
    "is_reply": false,
    "extraction_method": "youtube_api",
    "sentiment": "positive",
    "sentiment_score": 0.3524748384952545,
    "oem": "Ola Electric",
    "month": "2025-01"
  },
  {
    "text": "Where is my free robux link?",
    "author": "@Plushiepou647",
    "likes": 1,
    "time": 1755385987,
    "date": "2025-08-16 23:13:07",
    "video_id": "dQw4w9WgXcQ",
    "is_reply": false,
    "extraction_method": "youtube_api",
    "sentiment": "neutral",
    "sentiment_score": 0.7228524088859558,
    "oem": "Ola Electric",
    "month": "2025-01"
  },
  {
    "text": "I got rickrolled by AI",
    "author": "@joao-melo",
    "likes": 1,
    "time": 1755385790,
    "date": "2025-08-16 23:09:50",
    "video_id": "dQw4w9WgXcQ",
    "is_reply": false,
    "extraction_method": "youtube_api",
    "sentiment": "negative",
    "sentiment_score": 0.8178523778915405,
    "oem": "Ola Electric",
    "month": "2025-01"
  },
  {
    "text": "Quem veio por causa do mdt",
    "author": "@VeraLúcia-u5e7f",
    "likes": 0,
    "time": 1755385566,
    "date": "2025-08-16 23:06:06",
    "video_id": "dQw4w9WgXcQ",
    "is_reply": false,
    "extraction_method": "youtube_api",
    "sentiment": "neutral",
    "sentiment_score": 0.6795534491539001,
    "oem": "Ola Electric",
    "month": "2025-01"
  },
  {
    "text": "gulf of mexico 😍",
    "author": "@idontknowanymore8968",
    "likes": 1,
    "time": 1755385396,
    "date": "2025-08-16 23:03:16",
    "video_id": "dQw4w9WgXcQ",
    "is_reply": false,
    "extraction_method": "youtube_api",
    "sentiment": "positive",
    "sentiment_score": 0.5720748901367188,
    "oem": "Ola Electric",
    "month": "2025-01"
  }
]